{"FileInfo":{"Version":{"Major":1,"Minor":3,"Patch":1},"CreatedAt":"2024-04-01T23:55:36.6706026+02:00","UpdatedAt":"0001-01-01T00:00:00"},"streamer":{"name":"MichielVandeweert","id":66133267},"video":{"title":"3rd place","description":null,"id":"1043309521","created_at":"2021-06-02T11:57:50Z","start":0,"end":1612,"length":1612,"viewCount":36,"game":"Call of Duty: Warzone","chapters":[{"id":"","startMilliseconds":0,"lengthMilliseconds":1612000,"type":"GAME_CHANGE","description":"Call of Duty: Warzone","subDescription":"","thumbnailUrl":null,"gameId":"512710","gameDisplayName":"Call of Duty: Warzone","gameBoxArtUrl":"https://static-cdn.jtvnw.net/ttv-boxart/512710-40x53.jpg"}]},"comments":[{"_id":"Q8oK5x7ChBY-PQ","created_at":"2021-06-02T12:00:01.3665932Z","channel_id":"66133267","content_type":"video","content_id":"1043309521","content_offset_seconds":2,"commenter":{"display_name":"Zenix12580","_id":"94544880","name":"zenix12580","bio":null,"created_at":"2015-06-26T19:09:50.24858Z","updated_at":"2023-12-11T17:31:22.533384Z","logo":"https://static-cdn.jtvnw.net/jtv_user_pictures/bb91114a-3c4b-4570-83e8-f4673435f841-profile_image-300x300.png"},"message":{"body":"are u australia","bits_spent":0,"fragments":[{"text":"are u australia","emoticon":null}],"user_badges":[],"user_color":"#FF69B4","emoticons":[]}},{"_id":"kd4K5x7ChBYD1Q","created_at":"2021-06-02T12:00:01.4062436Z","channel_id":"66133267","content_type":"video","content_id":"1043309521","content_offset_seconds":6,"commenter":{"display_name":"シシシシシシシシシシシ","_id":"15439691","name":"fatstarl0rd","bio":"","created_at":"2010-09-10T22:17:59.278724Z","updated_at":"2024-04-01T21:40:29.763228Z","logo":"https://static-cdn.jtvnw.net/jtv_user_pictures/73482d9c-b2d2-49d6-a7fa-dde1abdca150-profile_image-300x300.png"},"message":{"body":"Moet oefenen voor mij Warzone toernooi nu. Ga proberen zoveel mogelijk te kijken op chat. :D","bits_spent":0,"fragments":[{"text":"Moet oefenen voor mij Warzone toernooi nu. Ga proberen zoveel mogelijk te kijken op chat. ","emoticon":null},{"text":":D","emoticon":{"emoticon_id":"555555560"}}],"user_badges":[{"_id":"moderator","version":"1"},{"_id":"subscriber","version":"3"},{"_id":"premium","version":"1"}],"user_color":"#FF69B4","emoticons":[{"_id":"555555560","begin":90,"end":93}]}},{"_id":"9ukK5x7ChBb_3g","created_at":"2021-06-02T12:00:01.4752553Z","channel_id":"66133267","content_type":"video","content_id":"1043309521","content_offset_seconds":7,"commenter":{"display_name":"zippyxcx","_id":"433361867","name":"zippyxcx","bio":" ","created_at":"2019-05-01T14:04:27.678622Z","updated_at":"2022-02-16T19:51:35.806274Z","logo":"https://static-cdn.jtvnw.net/jtv_user_pictures/1185dceb-33a6-4777-a6c4-6fc6fcfb830d-profile_image-300x300.png"},"message":{"body":"then just stop the hay","bits_spent":0,"fragments":[{"text":"then just stop the hay","emoticon":null}],"user_badges":[{"_id":"premium","version":"1"}],"user_color":"#00FF7F","emoticons":[]}},{"_id":"IvUK5x7ChBajHQ","created_at":"2021-06-02T12:00:01.5254913Z","channel_id":"66133267","content_type":"video","content_id":"1043309521","content_offset_seconds":11,"commenter":{"display_name":"nah_mat","_id":"574499034","name":"nah_mat","bio":"I think i will stream some day","created_at":"2020-08-28T22:04:44.621511Z","updated_at":"2024-03-17T21:40:57.268876Z","logo":"https://static-cdn.jtvnw.net/jtv_user_pictures/2fad1cce-90dd-45d8-8d35-fdc7cdb9e7c4-profile_image-300x300.jpeg"},"message":{"body":"Id love to be iraq rn :troll:","bits_spent":0,"fragments":[{"text":"Id love to be iraq rn :troll:","emoticon":null}],"user_badges":[],"user_color":null,"emoticons":[]}},{"_id":"KAAL5x7ChBalyw","created_at":"2021-06-02T12:00:01.6116349Z","channel_id":"66133267","content_type":"video","content_id":"1043309521","content_offset_seconds":17,"commenter":{"display_name":"siemenswek","_id":"74532248","name":"siemenswek","bio":"DAG, Ik ben Siemen, 23, software tester en fervent gamer. ik ben weliswaar dogwater in elke game die ik speel maar ben de beste entertainer ter wereld (van mijn huis)","created_at":"2014-11-05T14:25:08.031979Z","updated_at":"2024-04-01T11:44:06.480947Z","logo":"https://static-cdn.jtvnw.net/jtv_user_pictures/759a58ab-1907-4387-b7b0-65b026646281-profile_image-300x300.jpeg"},"message":{"body":"wa wordt moeilijk zonder mij @rocca017","bits_spent":0,"fragments":[{"text":"wa wordt moeilijk zonder mij ","emoticon":null},{"text":"@rocca017","emoticon":null}],"user_badges":[{"_id":"moderator","version":"1"}],"user_color":"#FF69B4","emoticons":[]}},{"_id":"8wsL5x7ChBYiog","created_at":"2021-06-02T12:00:01.6731668Z","channel_id":"66133267","content_type":"video","content_id":"1043309521","content_offset_seconds":30,"commenter":{"display_name":"letmedieeee2","_id":"654002187","name":"letmedieeee2","bio":null,"created_at":"2021-02-22T20:47:46.750729Z","updated_at":"2022-06-09T01:44:08.828997Z","logo":"https://static-cdn.jtvnw.net/user-default-pictures-uv/ce57700a-def9-11e9-842d-784f43822e80-profile_image-300x300.png"},"message":{"body":"yo how do you say your name michiel","bits_spent":0,"fragments":[{"text":"yo how do you say your name michiel","emoticon":null}],"user_badges":[],"user_color":null,"emoticons":[]}},{"_id":"OioL5x7ChBbNCw","created_at":"2021-06-02T12:00:01.7460227Z","channel_id":"66133267","content_type":"video","content_id":"1043309521","content_offset_seconds":32,"commenter":{"display_name":"Rocca017","_id":"195145656","name":"rocca017","bio":null,"created_at":"2018-02-07T01:14:37.608043Z","updated_at":"2024-03-12T16:30:24.177501Z","logo":"https://static-cdn.jtvnw.net/jtv_user_pictures/3ce9832e-9c4f-4c43-9853-f68f7787fcc9-profile_image-300x300.png"},"message":{"body":"@siemenswek iets te doen :D","bits_spent":0,"fragments":[{"text":"@siemenswek","emoticon":null},{"text":" iets te doen ","emoticon":null},{"text":":D","emoticon":{"emoticon_id":"555555560"}}],"user_badges":[{"_id":"moderator","version":"1"},{"_id":"subscriber","version":"6"},{"_id":"premium","version":"1"}],"user_color":"#693273","emoticons":[{"_id":"555555560","begin":25,"end":28}]}},{"_id":"KzUL5x7ChBbHVQ","created_at":"2021-06-02T12:00:01.8356914Z","channel_id":"66133267","content_type":"video","content_id":"1043309521","content_offset_seconds":39,"commenter":{"display_name":"jarnovde2","_id":"692415088","name":"jarnovde2","bio":null,"created_at":"2021-05-30T17:48:57.485364Z","updated_at":"2021-06-05T22:00:23.653156Z","logo":"https://static-cdn.jtvnw.net/user-default-pictures-uv/215b7342-def9-11e9-9a66-784f43822e80-profile_image-300x300.png"},"message":{"body":"Das nen echten belg eh de Michiel","bits_spent":0,"fragments":[{"text":"Das nen echten belg eh de Michiel","emoticon":null}],"user_badges":[],"user_color":null,"emoticons":[]}},{"_id":"u0AL5x7ChBboiQ","created_at":"2021-06-02T12:00:01.8916208Z","channel_id":"66133267","content_type":"video","content_id":"1043309521","content_offset_seconds":55,"commenter":{"display_name":"7MOZZ7","_id":"450366584","name":"7mozz7","bio":"","created_at":"2019-07-24T16:58:42.742044Z","updated_at":"2023-09-17T19:04:37.164474Z","logo":"https://static-cdn.jtvnw.net/jtv_user_pictures/266c5b30-b3b0-4ad4-bd40-486d5c640f75-profile_image-300x300.png"},"message":{"body":"Hi my friend","bits_spent":0,"fragments":[{"text":"Hi my friend","emoticon":null}],"user_badges":[],"user_color":null,"emoticons":[]}},{"_id":"uEsL5x7ChBbc1A","created_at":"2021-06-02T12:00:01.9430847Z","channel_id":"66133267","content_type":"video","content_id":"1043309521","content_offset_seconds":60,"commenter":{"display_name":"tim01062006","_id":"602141114","name":"tim01062006","bio":null,"created_at":"2020-10-31T15:48:09.182358Z","updated_at":"2020-10-31T15:48:57.287186Z","logo":"https://static-cdn.jtvnw.net/user-default-pictures-uv/998f01ae-def8-11e9-b95c-784f43822e80-profile_image-300x300.png"},"message":{"body":"The Mac 10 is a fking beast in warzone","bits_spent":0,"fragments":[{"text":"The Mac 10 is a fking beast in warzone","emoticon":null}],"user_badges":[],"user_color":null,"emoticons":[]}},{"_id":"GlcL5x7ChBZeUg","created_at":"2021-06-02T12:00:02.0179943Z","channel_id":"66133267","content_type":"video","content_id":"1043309521","content_offset_seconds":67,"commenter":{"display_name":"7MOZZ7","_id":"450366584","name":"7mozz7","bio":"","created_at":"2019-07-24T16:58:42.742044Z","updated_at":"2023-09-17T19:04:37.164474Z","logo":"https://static-cdn.jtvnw.net/jtv_user_pictures/266c5b30-b3b0-4ad4-bd40-486d5c640f75-profile_image-300x300.png"},"message":{"body":"How ya doing g","bits_spent":0,"fragments":[{"text":"How ya doing g","emoticon":null}],"user_badges":[],"user_color":null,"emoticons":[]}},{"_id":"JWIL5x7ChBakYQ","created_at":"2021-06-02T12:00:02.062176Z","channel_id":"66133267","content_type":"video","content_id":"1043309521","content_offset_seconds":69,"commenter":{"display_name":"siemenswek","_id":"74532248","name":"siemenswek","bio":"DAG, Ik ben Siemen, 23, software tester en fervent gamer. ik ben weliswaar dogwater in elke game die ik speel maar ben de beste entertainer ter wereld (van mijn huis)","created_at":"2014-11-05T14:25:08.031979Z","updated_at":"2024-04-01T11:44:06.480947Z","logo":"https://static-cdn.jtvnw.net/jtv_user_pictures/759a58ab-1907-4387-b7b0-65b026646281-profile_image-300x300.jpeg"},"message":{"body":"in game of in chat?","bits_spent":0,"fragments":[{"text":"in game of in chat?","emoticon":null}],"user_badges":[{"_id":"moderator","version":"1"}],"user_color":"#FF69B4","emoticons":[]}},{"_id":"PW0L5x7ChBbcxA","created_at":"2021-06-02T12:00:02.1436002Z","channel_id":"66133267","content_type":"video","content_id":"1043309521","content_offset_seconds":73,"commenter":{"display_name":"kingamsal8751","_id":"611511154","name":"kingamsal8751","bio":"","created_at":"2020-11-21T15:54:03.306156Z","updated_at":"2024-02-13T14:05:38.265356Z","logo":"https://static-cdn.jtvnw.net/jtv_user_pictures/02d1a32c-5f6e-4653-b2c0-758ab52994da-profile_image-300x300.png"},"message":{"body":"whats your favorite weapon?","bits_spent":0,"fragments":[{"text":"whats your favorite weapon?","emoticon":null}],"user_badges":[],"user_color":null,"emoticons":[]}},{"_id":"mXgL5x7ChBZodA","created_at":"2021-06-02T12:00:02.2024489Z","channel_id":"66133267","content_type":"video","content_id":"1043309521","content_offset_seconds":85,"commenter":{"display_name":"letmedieeee2","_id":"654002187","name":"letmedieeee2","bio":null,"created_at":"2021-02-22T20:47:46.750729Z","updated_at":"2022-06-09T01:44:08.828997Z","logo":"https://static-cdn.jtvnw.net/user-default-pictures-uv/ce57700a-def9-11e9-842d-784f43822e80-profile_image-300x300.png"},"message":{"body":"ohhhh alr that’s a cool name","bits_spent":0,"fragments":[{"text":"ohhhh alr that’s a cool name","emoticon":null}],"user_badges":[],"user_color":null,"emoticons":[]}},{"_id":"LoML5x7ChBYLsw","created_at":"2021-06-02T12:00:02.3387764Z","channel_id":"66133267","content_type":"video","content_id":"1043309521","content_offset_seconds":85,"commenter":{"display_name":"Rocca017","_id":"195145656","name":"rocca017","bio":null,"created_at":"2018-02-07T01:14:37.608043Z","updated_at":"2024-03-12T16:30:24.177501Z","logo":"https://static-cdn.jtvnw.net/jtv_user_pictures/3ce9832e-9c4f-4c43-9853-f68f7787fcc9-profile_image-300x300.png"},"message":{"body":"@siemenswek game :D waarom heeft die u in chat nodig :D","bits_spent":0,"fragments":[{"text":"@siemenswek","emoticon":null},{"text":" game ","emoticon":null},{"text":":D","emoticon":{"emoticon_id":"555555560"}},{"text":" waarom heeft die u in chat nodig ","emoticon":null},{"text":":D","emoticon":{"emoticon_id":"555555560"}}],"user_badges":[{"_id":"moderator","version":"1"},{"_id":"subscriber","version":"6"},{"_id":"premium","version":"1"}],"user_color":"#693273","emoticons":[{"_id":"555555560","begin":17,"end":20},{"_id":"555555560","begin":53,"end":56}]}},{"_id":"rI0L5x7ChBaLng","created_at":"2021-06-02T12:00:02.4587658Z","channel_id":"66133267","content_type":"video","content_id":"1043309521","content_offset_seconds":112,"commenter":{"display_name":"tim01062006","_id":"602141114","name":"tim01062006","bio":null,"created_at":"2020-10-31T15:48:09.182358Z","updated_at":"2020-10-31T15:48:57.287186Z","logo":"https://static-cdn.jtvnw.net/user-default-pictures-uv/998f01ae-def8-11e9-b95c-784f43822e80-profile_image-300x300.png"},"message":{"body":"Maar wrm praat je gwn niet nl?","bits_spent":0,"fragments":[{"text":"Maar wrm praat je gwn niet nl?","emoticon":null}],"user_badges":[],"user_color":null,"emoticons":[]}},{"_id":"qpgL5x7ChBbciQ","created_at":"2021-06-02T12:00:02.5186744Z","channel_id":"66133267","content_type":"video","content_id":"1043309521","content_offset_seconds":120,"commenter":{"display_name":"siemenswek","_id":"74532248","name":"siemenswek","bio":"DAG, Ik ben Siemen, 23, software tester en fervent gamer. ik ben weliswaar dogwater in elke game die ik speel maar ben de beste entertainer ter wereld (van mijn huis)","created_at":"2014-11-05T14:25:08.031979Z","updated_at":"2024-04-01T11:44:06.480947Z","logo":"https://static-cdn.jtvnw.net/jtv_user_pictures/759a58ab-1907-4387-b7b0-65b026646281-profile_image-300x300.jpeg"},"message":{"body":"omdat he weg moest ofzo","bits_spent":0,"fragments":[{"text":"omdat he weg moest ofzo","emoticon":null}],"user_badges":[{"_id":"moderator","version":"1"}],"user_color":"#FF69B4","emoticons":[]}},{"_id":"za8L5x7ChBbTDg","created_at":"2021-06-02T12:00:02.5715283Z","channel_id":"66133267","content_type":"video","content_id":"1043309521","content_offset_seconds":121,"commenter":{"display_name":"Rocca017","_id":"195145656","name":"rocca017","bio":null,"created_at":"2018-02-07T01:14:37.608043Z","updated_at":"2024-03-12T16:30:24.177501Z","logo":"https://static-cdn.jtvnw.net/jtv_user_pictures/3ce9832e-9c4f-4c43-9853-f68f7787fcc9-profile_image-300x300.png"},"message":{"body":"!partner","bits_spent":0,"fragments":[{"text":"!partner","emoticon":null}],"user_badges":[{"_id":"moderator","version":"1"},{"_id":"subscriber","version":"6"},{"_id":"premium","version":"1"}],"user_color":"#693273","emoticons":[]}},{"_id":"WLsL5x7ChBbTdQ","created_at":"2021-06-02T12:00:02.6436734Z","channel_id":"66133267","content_type":"video","content_id":"1043309521","content_offset_seconds":122,"commenter":{"display_name":"Nightbot","_id":"19264788","name":"nightbot","bio":"A chat moderation bot on Twitch. Visit nightbot.com to add Nightbot to your stream.","created_at":"2011-01-05T00:34:05.973707Z","updated_at":"2023-09-19T19:22:52.563766Z","logo":"https://static-cdn.jtvnw.net/jtv_user_pictures/nightbot-profile_image-2345338c09b4d468-300x300.png"},"message":{"body":"from the 13th of May, I am going to stream in english for a Partner Push! In the hopes i can request my Partner on the 13th of June ( My birthday) vanaf de 13de Mei ga ik in het Engels streamen voor een partner Push! In de hoop dat ik mijn Partner 13 Juni kan aanvragen! (Mijn verjaardag)","bits_spent":0,"fragments":[{"text":"from the 13th of May, I am going to stream in english for a Partner Push! In the hopes i can request my Partner on the 13th of June ( My birthday) vanaf de 13de Mei ga ik in het Engels streamen voor een partner Push! In de hoop dat ik mijn Partner 13 Juni kan aanvragen! (Mijn verjaardag)","emoticon":null}],"user_badges":[{"_id":"moderator","version":"1"},{"_id":"subscriber","version":"2"},{"_id":"partner","version":"1"}],"user_color":"#7C7CE1","emoticons":[]}},{"_id":"ncUL5x7ChBbX5Q","created_at":"2021-06-02T12:00:02.775708Z","channel_id":"66133267","content_type":"video","content_id":"1043309521","content_offset_seconds":136,"commenter":{"display_name":"nah_mat","_id":"574499034","name":"nah_mat","bio":"I think i will stream some day","created_at":"2020-08-28T22:04:44.621511Z","updated_at":"2024-03-17T21:40:57.268876Z","logo":"https://static-cdn.jtvnw.net/jtv_user_pictures/2fad1cce-90dd-45d8-8d35-fdc7cdb9e7c4-profile_image-300x300.jpeg"},"message":{"body":"kun je een ppsh-game-uitdaging doen, het wordt moeilijk omdat dat pistool doodoo is?","bits_spent":0,"fragments":[{"text":"kun je een ppsh-game-uitdaging doen, het wordt moeilijk omdat dat pistool doodoo is?","emoticon":null}],"user_badges":[],"user_color":null,"emoticons":[]}},{"_id":"G9AL5x7ChBavfw","created_at":"2021-06-02T12:00:02.8368812Z","channel_id":"66133267","content_type":"video","content_id":"1043309521","content_offset_seconds":145,"commenter":{"display_name":"Rocca017","_id":"195145656","name":"rocca017","bio":null,"created_at":"2018-02-07T01:14:37.608043Z","updated_at":"2024-03-12T16:30:24.177501Z","logo":"https://static-cdn.jtvnw.net/jtv_user_pictures/3ce9832e-9c4f-4c43-9853-f68f7787fcc9-profile_image-300x300.png"},"message":{"body":"@siemenswek als Ali ging zingen ging ik weg :D hhahaha","bits_spent":0,"fragments":[{"text":"@siemenswek","emoticon":null},{"text":" als Ali ging zingen ging ik weg ","emoticon":null},{"text":":D","emoticon":{"emoticon_id":"555555560"}},{"text":" hhahaha","emoticon":null}],"user_badges":[{"_id":"moderator","version":"1"},{"_id":"subscriber","version":"6"},{"_id":"premium","version":"1"}],"user_color":"#693273","emoticons":[{"_id":"555555560","begin":44,"end":47}]}},{"_id":"GtsL5x7ChBasww","created_at":"2021-06-02T12:00:02.9079665Z","channel_id":"66133267","content_type":"video","content_id":"1043309521","content_offset_seconds":163,"commenter":{"display_name":"Zenix12580","_id":"94544880","name":"zenix12580","bio":null,"created_at":"2015-06-26T19:09:50.24858Z","updated_at":"2023-12-11T17:31:22.533384Z","logo":"https://static-cdn.jtvnw.net/jtv_user_pictures/bb91114a-3c4b-4570-83e8-f4673435f841-profile_image-300x300.png"},"message":{"body":"do you sometimes use the amax?","bits_spent":0,"fragments":[{"text":"do you sometimes use the amax?","emoticon":null}],"user_badges":[],"user_color":"#FF69B4","emoticons":[]}},{"_id":"N-YL5x7ChBZ9Mg","created_at":"2021-06-02T12:00:02.9820519Z","channel_id":"66133267","content_type":"video","content_id":"1043309521","content_offset_seconds":172,"commenter":{"display_name":"Rocca017","_id":"195145656","name":"rocca017","bio":null,"created_at":"2018-02-07T01:14:37.608043Z","updated_at":"2024-03-12T16:30:24.177501Z","logo":"https://static-cdn.jtvnw.net/jtv_user_pictures/3ce9832e-9c4f-4c43-9853-f68f7787fcc9-profile_image-300x300.png"},"message":{"body":"yes he does","bits_spent":0,"fragments":[{"text":"yes he does","emoticon":null}],"user_badges":[{"_id":"moderator","version":"1"},{"_id":"subscriber","version":"6"},{"_id":"premium","version":"1"}],"user_color":"#693273","emoticons":[]}},{"_id":"-PEL5x7ChBb2AQ","created_at":"2021-06-02T12:00:03.0439584Z","channel_id":"66133267","content_type":"video","content_id":"1043309521","content_offset_seconds":187,"commenter":{"display_name":"nah_mat","_id":"574499034","name":"nah_mat","bio":"I think i will stream some day","created_at":"2020-08-28T22:04:44.621511Z","updated_at":"2024-03-17T21:40:57.268876Z","logo":"https://static-cdn.jtvnw.net/jtv_user_pictures/2fad1cce-90dd-45d8-8d35-fdc7cdb9e7c4-profile_image-300x300.jpeg"},"message":{"body":"Je zou de XM4 moeten gebruiken, dat pistool is echt pog","bits_spent":0,"fragments":[{"text":"Je zou de XM4 moeten gebruiken, dat pistool is echt pog","emoticon":null}],"user_badges":[],"user_color":null,"emoticons":[]}},{"_id":"6PwL5x7ChBZ6Cg","created_at":"2021-06-02T12:00:03.0984457Z","channel_id":"66133267","content_type":"video","content_id":"1043309521","content_offset_seconds":200,"commenter":{"display_name":"Rocca017","_id":"195145656","name":"rocca017","bio":null,"created_at":"2018-02-07T01:14:37.608043Z","updated_at":"2024-03-12T16:30:24.177501Z","logo":"https://static-cdn.jtvnw.net/jtv_user_pictures/3ce9832e-9c4f-4c43-9853-f68f7787fcc9-profile_image-300x300.png"},"message":{"body":"@nah_mat doet hij ook ;)","bits_spent":0,"fragments":[{"text":"@nah_mat","emoticon":null},{"text":" doet hij ook ","emoticon":null},{"text":";)","emoticon":{"emoticon_id":"555555589"}}],"user_badges":[{"_id":"moderator","version":"1"},{"_id":"subscriber","version":"6"},{"_id":"premium","version":"1"}],"user_color":"#693273","emoticons":[{"_id":"555555589","begin":22,"end":25}]}},{"_id":"qwgM5x7ChBYxdg","created_at":"2021-06-02T12:00:03.167579Z","channel_id":"66133267","content_type":"video","content_id":"1043309521","content_offset_seconds":206,"commenter":{"display_name":"nah_mat","_id":"574499034","name":"nah_mat","bio":"I think i will stream some day","created_at":"2020-08-28T22:04:44.621511Z","updated_at":"2024-03-17T21:40:57.268876Z","logo":"https://static-cdn.jtvnw.net/jtv_user_pictures/2fad1cce-90dd-45d8-8d35-fdc7cdb9e7c4-profile_image-300x300.jpeg"},"message":{"body":"ok","bits_spent":0,"fragments":[{"text":"ok","emoticon":null}],"user_badges":[],"user_color":null,"emoticons":[]}},{"_id":"yxMM5x7ChBb4Pw","created_at":"2021-06-02T12:00:03.1956014Z","channel_id":"66133267","content_type":"video","content_id":"1043309521","content_offset_seconds":215,"commenter":{"display_name":"Rocca017","_id":"195145656","name":"rocca017","bio":null,"created_at":"2018-02-07T01:14:37.608043Z","updated_at":"2024-03-12T16:30:24.177501Z","logo":"https://static-cdn.jtvnw.net/jtv_user_pictures/3ce9832e-9c4f-4c43-9853-f68f7787fcc9-profile_image-300x300.png"},"message":{"body":"vaak met de kar","bits_spent":0,"fragments":[{"text":"vaak met de kar","emoticon":null}],"user_badges":[{"_id":"moderator","version":"1"},{"_id":"subscriber","version":"6"},{"_id":"premium","version":"1"}],"user_color":"#693273","emoticons":[]}},{"_id":"QB4M5x7ChBaTZw","created_at":"2021-06-02T12:00:03.2470539Z","channel_id":"66133267","content_type":"video","content_id":"1043309521","content_offset_seconds":233,"commenter":{"display_name":"nathan_morgan_drake","_id":"609189493","name":"nathan_morgan_drake","bio":"in shambhala rn","created_at":"2020-11-15T18:08:10.219618Z","updated_at":"2024-03-21T02:43:11.67184Z","logo":"https://static-cdn.jtvnw.net/jtv_user_pictures/30db8b6f-9179-415f-84d1-ea5e80b7e073-profile_image-300x300.jpeg"},"message":{"body":"rosyroYAY rosyroYAY rosyroYAY rosyroYAY rosyroYAY rosyroYAY rosyroYAY","bits_spent":0,"fragments":[{"text":"rosyroYAY","emoticon":{"emoticon_id":"307766614"}},{"text":" ","emoticon":null},{"text":"rosyroYAY","emoticon":{"emoticon_id":"307766614"}},{"text":" ","emoticon":null},{"text":"rosyroYAY","emoticon":{"emoticon_id":"307766614"}},{"text":" ","emoticon":null},{"text":"rosyroYAY","emoticon":{"emoticon_id":"307766614"}},{"text":" ","emoticon":null},{"text":"rosyroYAY","emoticon":{"emoticon_id":"307766614"}},{"text":" ","emoticon":null},{"text":"rosyroYAY","emoticon":{"emoticon_id":"307766614"}},{"text":" ","emoticon":null},{"text":"rosyroYAY","emoticon":{"emoticon_id":"307766614"}}],"user_badges":[],"user_color":"#0000FF","emoticons":[{"_id":"307766614","begin":0,"end":10},{"_id":"307766614","begin":10,"end":20},{"_id":"307766614","begin":20,"end":30},{"_id":"307766614","begin":30,"end":40},{"_id":"307766614","begin":40,"end":50},{"_id":"307766614","begin":50,"end":60},{"_id":"307766614","begin":60,"end":70}]}},{"_id":"mSgM5x7ChBa66Q","created_at":"2021-06-02T12:00:03.2909417Z","channel_id":"66133267","content_type":"video","content_id":"1043309521","content_offset_seconds":245,"commenter":{"display_name":"zippyxcx","_id":"433361867","name":"zippyxcx","bio":" ","created_at":"2019-05-01T14:04:27.678622Z","updated_at":"2022-02-16T19:51:35.806274Z","logo":"https://static-cdn.jtvnw.net/jtv_user_pictures/1185dceb-33a6-4777-a6c4-6fc6fcfb830d-profile_image-300x300.png"},"message":{"body":"I love your streams","bits_spent":0,"fragments":[{"text":"I love your streams","emoticon":null}],"user_badges":[{"_id":"premium","version":"1"}],"user_color":"#00FF7F","emoticons":[]}},{"_id":"bjMM5x7ChBbcgg","created_at":"2021-06-02T12:00:03.3226595Z","channel_id":"66133267","content_type":"video","content_id":"1043309521","content_offset_seconds":247,"commenter":{"display_name":"nah_mat","_id":"574499034","name":"nah_mat","bio":"I think i will stream some day","created_at":"2020-08-28T22:04:44.621511Z","updated_at":"2024-03-17T21:40:57.268876Z","logo":"https://static-cdn.jtvnw.net/jtv_user_pictures/2fad1cce-90dd-45d8-8d35-fdc7cdb9e7c4-profile_image-300x300.jpeg"},"message":{"body":"aaa i don't speak dutch i was just using Google translate","bits_spent":0,"fragments":[{"text":"aaa i don't speak dutch i was just using Google translate","emoticon":null}],"user_badges":[],"user_color":null,"emoticons":[]}},{"_id":"3D0M5x7ChBYXYg","created_at":"2021-06-02T12:00:03.3712101Z","channel_id":"66133267","content_type":"video","content_id":"1043309521","content_offset_seconds":271,"commenter":{"display_name":"Rocca017","_id":"195145656","name":"rocca017","bio":null,"created_at":"2018-02-07T01:14:37.608043Z","updated_at":"2024-03-12T16:30:24.177501Z","logo":"https://static-cdn.jtvnw.net/jtv_user_pictures/3ce9832e-9c4f-4c43-9853-f68f7787fcc9-profile_image-300x300.png"},"message":{"body":"just talk english or dutch :)","bits_spent":0,"fragments":[{"text":"just talk english or dutch ","emoticon":null},{"text":":)","emoticon":{"emoticon_id":"1"}}],"user_badges":[{"_id":"moderator","version":"1"},{"_id":"subscriber","version":"6"},{"_id":"premium","version":"1"}],"user_color":"#693273","emoticons":[{"_id":"1","begin":27,"end":30}]}},{"_id":"8EgM5x7ChBbulA","created_at":"2021-06-02T12:00:03.4340674Z","channel_id":"66133267","content_type":"video","content_id":"1043309521","content_offset_seconds":295,"commenter":{"display_name":"nah_mat","_id":"574499034","name":"nah_mat","bio":"I think i will stream some day","created_at":"2020-08-28T22:04:44.621511Z","updated_at":"2024-03-17T21:40:57.268876Z","logo":"https://static-cdn.jtvnw.net/jtv_user_pictures/2fad1cce-90dd-45d8-8d35-fdc7cdb9e7c4-profile_image-300x300.jpeg"},"message":{"body":"ok","bits_spent":0,"fragments":[{"text":"ok","emoticon":null}],"user_badges":[],"user_color":null,"emoticons":[]}},{"_id":"C1QM5x7ChBY69w","created_at":"2021-06-02T12:00:03.4632818Z","channel_id":"66133267","content_type":"video","content_id":"1043309521","content_offset_seconds":312,"commenter":{"display_name":"nah_mat","_id":"574499034","name":"nah_mat","bio":"I think i will stream some day","created_at":"2020-08-28T22:04:44.621511Z","updated_at":"2024-03-17T21:40:57.268876Z","logo":"https://static-cdn.jtvnw.net/jtv_user_pictures/2fad1cce-90dd-45d8-8d35-fdc7cdb9e7c4-profile_image-300x300.jpeg"},"message":{"body":"is dutch a hard language to learn","bits_spent":0,"fragments":[{"text":"is dutch a hard language to learn","emoticon":null}],"user_badges":[],"user_color":null,"emoticons":[]}},{"_id":"oV4M5x7ChBZlGw","created_at":"2021-06-02T12:00:03.5019853Z","channel_id":"66133267","content_type":"video","content_id":"1043309521","content_offset_seconds":322,"commenter":{"display_name":"nah_mat","_id":"574499034","name":"nah_mat","bio":"I think i will stream some day","created_at":"2020-08-28T22:04:44.621511Z","updated_at":"2024-03-17T21:40:57.268876Z","logo":"https://static-cdn.jtvnw.net/jtv_user_pictures/2fad1cce-90dd-45d8-8d35-fdc7cdb9e7c4-profile_image-300x300.jpeg"},"message":{"body":"all i know is the memes","bits_spent":0,"fragments":[{"text":"all i know is the memes","emoticon":null}],"user_badges":[],"user_color":null,"emoticons":[]}},{"_id":"72kM5x7ChBZhkg","created_at":"2021-06-02T12:00:03.542723Z","channel_id":"66133267","content_type":"video","content_id":"1043309521","content_offset_seconds":325,"commenter":{"display_name":"Rocca017","_id":"195145656","name":"rocca017","bio":null,"created_at":"2018-02-07T01:14:37.608043Z","updated_at":"2024-03-12T16:30:24.177501Z","logo":"https://static-cdn.jtvnw.net/jtv_user_pictures/3ce9832e-9c4f-4c43-9853-f68f7787fcc9-profile_image-300x300.png"},"message":{"body":"yes it is","bits_spent":0,"fragments":[{"text":"yes it is","emoticon":null}],"user_badges":[{"_id":"moderator","version":"1"},{"_id":"subscriber","version":"6"},{"_id":"premium","version":"1"}],"user_color":"#693273","emoticons":[]}},{"_id":"i3QM5x7ChBY4Cw","created_at":"2021-06-02T12:00:03.5832562Z","channel_id":"66133267","content_type":"video","content_id":"1043309521","content_offset_seconds":326,"commenter":{"display_name":"frankz_071","_id":"615028132","name":"frankz_071","bio":null,"created_at":"2020-11-30T23:16:37.77627Z","updated_at":"2021-08-08T03:02:54.025912Z","logo":"https://static-cdn.jtvnw.net/user-default-pictures-uv/41780b5a-def8-11e9-94d9-784f43822e80-profile_image-300x300.png"},"message":{"body":"Do you like playing more battle royal or rebirth island?","bits_spent":0,"fragments":[{"text":"Do you like playing more battle royal or rebirth island?","emoticon":null}],"user_badges":[],"user_color":null,"emoticons":[]}},{"_id":"034M5x7ChBasBQ","created_at":"2021-06-02T12:00:03.637047Z","channel_id":"66133267","content_type":"video","content_id":"1043309521","content_offset_seconds":332,"commenter":{"display_name":"richmanov","_id":"501070698","name":"richmanov","bio":null,"created_at":"2020-03-19T17:27:43.159326Z","updated_at":"2021-06-01T19:44:44.658312Z","logo":"https://static-cdn.jtvnw.net/user-default-pictures-uv/ebb84563-db81-4b9c-8940-64ed33ccfc7b-profile_image-300x300.png"},"message":{"body":"nein xd","bits_spent":0,"fragments":[{"text":"nein xd","emoticon":null}],"user_badges":[],"user_color":null,"emoticons":[]}},{"_id":"KYkM5x7ChBbpHQ","created_at":"2021-06-02T12:00:03.6868789Z","channel_id":"66133267","content_type":"video","content_id":"1043309521","content_offset_seconds":343,"commenter":{"display_name":"wendyke1991","_id":"165771615","name":"wendyke1991","bio":"","created_at":"2017-07-20T12:36:32.473418Z","updated_at":"2023-06-02T18:38:30.385027Z","logo":"https://static-cdn.jtvnw.net/jtv_user_pictures/3e30bdf3-43d7-4387-ba14-4e9cd7ab4366-profile_image-300x300.png"},"message":{"body":"lodeout werkt niet meer op garage??","bits_spent":0,"fragments":[{"text":"lodeout werkt niet meer op garage??","emoticon":null}],"user_badges":[{"_id":"subscriber","version":"3"}],"user_color":"#8A2BE2","emoticons":[]}},{"_id":"vbYllB_ChBa8tA","created_at":"2021-06-02T12:00:03.8114102Z","channel_id":"66133267","content_type":"video","content_id":"1043309521","content_offset_seconds":350,"commenter":{"display_name":"nah_mat","_id":"574499034","name":"nah_mat","bio":"I think i will stream some day","created_at":"2020-08-28T22:04:44.621511Z","updated_at":"2024-03-17T21:40:57.268876Z","logo":"https://static-cdn.jtvnw.net/jtv_user_pictures/2fad1cce-90dd-45d8-8d35-fdc7cdb9e7c4-profile_image-300x300.jpeg"},"message":{"body":"a","bits_spent":0,"fragments":[{"text":"a","emoticon":null}],"user_badges":[],"user_color":null,"emoticons":[]}},{"_id":"-dMllB_ChBYmsg","created_at":"2021-06-02T12:00:03.8534399Z","channel_id":"66133267","content_type":"video","content_id":"1043309521","content_offset_seconds":366,"commenter":{"display_name":"Rocca017","_id":"195145656","name":"rocca017","bio":null,"created_at":"2018-02-07T01:14:37.608043Z","updated_at":"2024-03-12T16:30:24.177501Z","logo":"https://static-cdn.jtvnw.net/jtv_user_pictures/3ce9832e-9c4f-4c43-9853-f68f7787fcc9-profile_image-300x300.png"},"message":{"body":"denk het wel @wendyke1991","bits_spent":0,"fragments":[{"text":"denk het wel ","emoticon":null},{"text":"@wendyke1991","emoticon":null}],"user_badges":[{"_id":"moderator","version":"1"},{"_id":"subscriber","version":"6"},{"_id":"premium","version":"1"}],"user_color":"#693273","emoticons":[]}},{"_id":"d98llB_ChBanNQ","created_at":"2021-06-02T12:00:03.9096455Z","channel_id":"66133267","content_type":"video","content_id":"1043309521","content_offset_seconds":367,"commenter":{"display_name":"Nightbot","_id":"19264788","name":"nightbot","bio":"A chat moderation bot on Twitch. Visit nightbot.com to add Nightbot to your stream.","created_at":"2011-01-05T00:34:05.973707Z","updated_at":"2023-09-19T19:22:52.563766Z","logo":"https://static-cdn.jtvnw.net/jtv_user_pictures/nightbot-profile_image-2345338c09b4d468-300x300.png"},"message":{"body":"follow all my socials here! https://linktr.ee/MichielVandeweert","bits_spent":0,"fragments":[{"text":"follow all my socials here! ","emoticon":null},{"text":"https://linktr.ee/MichielVandeweert","emoticon":null}],"user_badges":[{"_id":"moderator","version":"1"},{"_id":"subscriber","version":"2"},{"_id":"partner","version":"1"}],"user_color":"#7C7CE1","emoticons":[]}},{"_id":"r-ollB_ChBbFew","created_at":"2021-06-02T12:00:03.9514736Z","channel_id":"66133267","content_type":"video","content_id":"1043309521","content_offset_seconds":369,"commenter":{"display_name":"wendyke1991","_id":"165771615","name":"wendyke1991","bio":"","created_at":"2017-07-20T12:36:32.473418Z","updated_at":"2023-06-02T18:38:30.385027Z","logo":"https://static-cdn.jtvnw.net/jtv_user_pictures/3e30bdf3-43d7-4387-ba14-4e9cd7ab4366-profile_image-300x300.png"},"message":{"body":"ooh ok","bits_spent":0,"fragments":[{"text":"ooh ok","emoticon":null}],"user_badges":[{"_id":"subscriber","version":"3"}],"user_color":"#8A2BE2","emoticons":[]}},{"_id":"gfYllB_ChBaNeQ","created_at":"2021-06-02T12:00:03.9887031Z","channel_id":"66133267","content_type":"video","content_id":"1043309521","content_offset_seconds":419,"commenter":{"display_name":"Nightbot","_id":"19264788","name":"nightbot","bio":"A chat moderation bot on Twitch. Visit nightbot.com to add Nightbot to your stream.","created_at":"2011-01-05T00:34:05.973707Z","updated_at":"2023-09-19T19:22:52.563766Z","logo":"https://static-cdn.jtvnw.net/jtv_user_pictures/nightbot-profile_image-2345338c09b4d468-300x300.png"},"message":{"body":"have you seen my latest youtube video yet? NO? go watch it then!! https://www.youtube.com/watch?v=AkdL2AGDzPM","bits_spent":0,"fragments":[{"text":"have you seen my latest youtube video yet? NO? go watch it then!! ","emoticon":null},{"text":"https://www.youtube.com/watch?v=AkdL2AGDzPM","emoticon":null}],"user_badges":[{"_id":"moderator","version":"1"},{"_id":"subscriber","version":"2"},{"_id":"partner","version":"1"}],"user_color":"#7C7CE1","emoticons":[]}},{"_id":"kQImlB_ChBar0Q","created_at":"2021-06-02T12:00:04.030673Z","channel_id":"66133267","content_type":"video","content_id":"1043309521","content_offset_seconds":427,"commenter":{"display_name":"frankz_071","_id":"615028132","name":"frankz_071","bio":null,"created_at":"2020-11-30T23:16:37.77627Z","updated_at":"2021-08-08T03:02:54.025912Z","logo":"https://static-cdn.jtvnw.net/user-default-pictures-uv/41780b5a-def8-11e9-94d9-784f43822e80-profile_image-300x300.png"},"message":{"body":"What do you think the next meta gun will be?","bits_spent":0,"fragments":[{"text":"What do you think the next meta gun will be?","emoticon":null}],"user_badges":[],"user_color":null,"emoticons":[]}},{"_id":"yw0mlB_ChBZnCw","created_at":"2021-06-02T12:00:04.084994Z","channel_id":"66133267","content_type":"video","content_id":"1043309521","content_offset_seconds":451,"commenter":{"display_name":"elheenry","_id":"550555526","name":"elheenry","bio":"Hola, soy Henry y me gusta entretener y sacar una sonrisa\uD83D\uDE01","created_at":"2020-07-03T04:28:52.32938Z","updated_at":"2023-12-08T01:28:01.121778Z","logo":"https://static-cdn.jtvnw.net/jtv_user_pictures/e35e848f-51fb-43c0-9fe2-66922dd09aae-profile_image-300x300.png"},"message":{"body":"Bro you’re from tiktok of the Mac 10?\uD83E\uDD14","bits_spent":0,"fragments":[{"text":"Bro you’re from tiktok of the Mac 10?\uD83E\uDD14","emoticon":null}],"user_badges":[],"user_color":"#1E90FF","emoticons":[]}},{"_id":"vRgmlB_ChBZbLQ","created_at":"2021-06-02T12:00:04.1668057Z","channel_id":"66133267","content_type":"video","content_id":"1043309521","content_offset_seconds":460,"commenter":{"display_name":"putin__09","_id":"571244458","name":"putin__09","bio":null,"created_at":"2020-08-22T21:42:55.639468Z","updated_at":"2021-06-25T14:13:29.66901Z","logo":"https://static-cdn.jtvnw.net/user-default-pictures-uv/75305d54-c7cc-40d1-bb9c-91fbe85943c7-profile_image-300x300.png"},"message":{"body":"i think finn","bits_spent":0,"fragments":[{"text":"i think finn","emoticon":null}],"user_badges":[],"user_color":null,"emoticons":[]}},{"_id":"2yMmlB_ChBZPog","created_at":"2021-06-02T12:00:04.2705155Z","channel_id":"66133267","content_type":"video","content_id":"1043309521","content_offset_seconds":479,"commenter":{"display_name":"Rocca017","_id":"195145656","name":"rocca017","bio":null,"created_at":"2018-02-07T01:14:37.608043Z","updated_at":"2024-03-12T16:30:24.177501Z","logo":"https://static-cdn.jtvnw.net/jtv_user_pictures/3ce9832e-9c4f-4c43-9853-f68f7787fcc9-profile_image-300x300.png"},"message":{"body":"@elheenry he got edited on that clip ...","bits_spent":0,"fragments":[{"text":"@elheenry","emoticon":null},{"text":" he got edited on that clip ...","emoticon":null}],"user_badges":[{"_id":"moderator","version":"1"},{"_id":"subscriber","version":"6"},{"_id":"premium","version":"1"}],"user_color":"#693273","emoticons":[]}},{"_id":"gS4mlB_ChBZXlQ","created_at":"2021-06-02T12:00:04.3290863Z","channel_id":"66133267","content_type":"video","content_id":"1043309521","content_offset_seconds":566,"commenter":{"display_name":"elheenry","_id":"550555526","name":"elheenry","bio":"Hola, soy Henry y me gusta entretener y sacar una sonrisa\uD83D\uDE01","created_at":"2020-07-03T04:28:52.32938Z","updated_at":"2023-12-08T01:28:01.121778Z","logo":"https://static-cdn.jtvnw.net/jtv_user_pictures/e35e848f-51fb-43c0-9fe2-66922dd09aae-profile_image-300x300.png"},"message":{"body":"I see a lot of clips of the Mac 10 bro\uD83D\uDE2F","bits_spent":0,"fragments":[{"text":"I see a lot of clips of the Mac 10 bro\uD83D\uDE2F","emoticon":null}],"user_badges":[],"user_color":"#1E90FF","emoticons":[]}},{"_id":"5jkmlB_ChBZHQA","created_at":"2021-06-02T12:00:04.3774792Z","channel_id":"66133267","content_type":"video","content_id":"1043309521","content_offset_seconds":626,"commenter":{"display_name":"coinautumn123","_id":"634285468","name":"coinautumn123","bio":null,"created_at":"2021-01-10T09:47:19.285552Z","updated_at":"2023-11-07T19:48:18.974639Z","logo":"https://static-cdn.jtvnw.net/user-default-pictures-uv/ebb84563-db81-4b9c-8940-64ed33ccfc7b-profile_image-300x300.png"},"message":{"body":"Hiiiiiii","bits_spent":0,"fragments":[{"text":"Hiiiiiii","emoticon":null}],"user_badges":[],"user_color":null,"emoticons":[]}},{"_id":"akUmlB_ChBaCLA","created_at":"2021-06-02T12:00:04.4200417Z","channel_id":"66133267","content_type":"video","content_id":"1043309521","content_offset_seconds":629,"commenter":{"display_name":"drizzo_fn","_id":"693049921","name":"drizzo_fn","bio":null,"created_at":"2021-06-01T19:48:26.079088Z","updated_at":"2022-03-06T22:17:48.637437Z","logo":"https://static-cdn.jtvnw.net/user-default-pictures-uv/75305d54-c7cc-40d1-bb9c-91fbe85943c7-profile_image-300x300.png"},"message":{"body":"Yo","bits_spent":0,"fragments":[{"text":"Yo","emoticon":null}],"user_badges":[],"user_color":null,"emoticons":[]}},{"_id":"QVEmlB_ChBZWtg","created_at":"2021-06-02T12:00:04.4580179Z","channel_id":"66133267","content_type":"video","content_id":"1043309521","content_offset_seconds":660,"commenter":{"display_name":"savagenoahbruh","_id":"666330674","name":"savagenoahbruh","bio":null,"created_at":"2021-03-24T13:00:24.988046Z","updated_at":"2024-01-26T16:49:14.913675Z","logo":"https://static-cdn.jtvnw.net/user-default-pictures-uv/de130ab0-def7-11e9-b668-784f43822e80-profile_image-300x300.png"},"message":{"body":"yooo how are you \uD83D\uDE42","bits_spent":0,"fragments":[{"text":"yooo how are you \uD83D\uDE42","emoticon":null}],"user_badges":[],"user_color":null,"emoticons":[]}},{"_id":"7lsmlB_ChBYCSg","created_at":"2021-06-02T12:00:04.5099613Z","channel_id":"66133267","content_type":"video","content_id":"1043309521","content_offset_seconds":671,"commenter":{"display_name":"drizzo_fn","_id":"693049921","name":"drizzo_fn","bio":null,"created_at":"2021-06-01T19:48:26.079088Z","updated_at":"2022-03-06T22:17:48.637437Z","logo":"https://static-cdn.jtvnw.net/user-default-pictures-uv/75305d54-c7cc-40d1-bb9c-91fbe85943c7-profile_image-300x300.png"},"message":{"body":"Me","bits_spent":0,"fragments":[{"text":"Me","emoticon":null}],"user_badges":[],"user_color":null,"emoticons":[]}},{"_id":"mWcmlB_ChBaGog","created_at":"2021-06-02T12:00:04.5416742Z","channel_id":"66133267","content_type":"video","content_id":"1043309521","content_offset_seconds":694,"commenter":{"display_name":"frankz_071","_id":"615028132","name":"frankz_071","bio":null,"created_at":"2020-11-30T23:16:37.77627Z","updated_at":"2021-08-08T03:02:54.025912Z","logo":"https://static-cdn.jtvnw.net/user-default-pictures-uv/41780b5a-def8-11e9-94d9-784f43822e80-profile_image-300x300.png"},"message":{"body":"Do you have a ps5?","bits_spent":0,"fragments":[{"text":"Do you have a ps5?","emoticon":null}],"user_badges":[],"user_color":null,"emoticons":[]}},{"_id":"THImlB_ChBaE_w","created_at":"2021-06-02T12:00:04.6035633Z","channel_id":"66133267","content_type":"video","content_id":"1043309521","content_offset_seconds":700,"commenter":{"display_name":"savagenoahbruh","_id":"666330674","name":"savagenoahbruh","bio":null,"created_at":"2021-03-24T13:00:24.988046Z","updated_at":"2024-01-26T16:49:14.913675Z","logo":"https://static-cdn.jtvnw.net/user-default-pictures-uv/de130ab0-def7-11e9-b668-784f43822e80-profile_image-300x300.png"},"message":{"body":"you can just call me noah but im good","bits_spent":0,"fragments":[{"text":"you can just call me noah but im good","emoticon":null}],"user_badges":[],"user_color":null,"emoticons":[]}},{"_id":"FnwmlB_ChBZaLg","created_at":"2021-06-02T12:00:04.6425613Z","channel_id":"66133267","content_type":"video","content_id":"1043309521","content_offset_seconds":755,"commenter":{"display_name":"maxxxii64","_id":"536284763","name":"maxxxii64","bio":null,"created_at":"2020-05-27T16:08:29.71769Z","updated_at":"2024-03-29T21:30:58.47064Z","logo":"https://static-cdn.jtvnw.net/user-default-pictures-uv/215b7342-def9-11e9-9a66-784f43822e80-profile_image-300x300.png"},"message":{"body":"hi","bits_spent":0,"fragments":[{"text":"hi","emoticon":null}],"user_badges":[],"user_color":"#00FF7F","emoticons":[]}},{"_id":"8oUmlB_ChBZyCw","created_at":"2021-06-02T12:00:04.6786138Z","channel_id":"66133267","content_type":"video","content_id":"1043309521","content_offset_seconds":784,"commenter":{"display_name":"mini_shmushi","_id":"530113451","name":"mini_shmushi","bio":null,"created_at":"2020-05-13T16:20:26.349744Z","updated_at":"2021-09-11T18:11:07.270363Z","logo":"https://static-cdn.jtvnw.net/user-default-pictures-uv/ead5c8b2-a4c9-4724-b1dd-9f00b46cbd3d-profile_image-300x300.png"},"message":{"body":"hi michel","bits_spent":0,"fragments":[{"text":"hi michel","emoticon":null}],"user_badges":[],"user_color":null,"emoticons":[]}},{"_id":"k5AmlB_ChBYlLQ","created_at":"2021-06-02T12:00:04.7219108Z","channel_id":"66133267","content_type":"video","content_id":"1043309521","content_offset_seconds":791,"commenter":{"display_name":"loumoens","_id":"631617218","name":"loumoens","bio":null,"created_at":"2021-01-05T19:41:48.570158Z","updated_at":"2022-05-12T17:59:16.274538Z","logo":"https://static-cdn.jtvnw.net/user-default-pictures-uv/ebb84563-db81-4b9c-8940-64ed33ccfc7b-profile_image-300x300.png"},"message":{"body":"do u use ram7","bits_spent":0,"fragments":[{"text":"do u use ram7","emoticon":null}],"user_badges":[{"_id":"subscriber","version":"0"}],"user_color":null,"emoticons":[]}},{"_id":"opsmlB_ChBZbwg","created_at":"2021-06-02T12:00:04.7922016Z","channel_id":"66133267","content_type":"video","content_id":"1043309521","content_offset_seconds":795,"commenter":{"display_name":"loumoens","_id":"631617218","name":"loumoens","bio":null,"created_at":"2021-01-05T19:41:48.570158Z","updated_at":"2022-05-12T17:59:16.274538Z","logo":"https://static-cdn.jtvnw.net/user-default-pictures-uv/ebb84563-db81-4b9c-8940-64ed33ccfc7b-profile_image-300x300.png"},"message":{"body":"?","bits_spent":0,"fragments":[{"text":"?","emoticon":null}],"user_badges":[{"_id":"subscriber","version":"0"}],"user_color":null,"emoticons":[]}},{"_id":"5KUmlB_ChBadUQ","created_at":"2021-06-02T12:00:04.8452096Z","channel_id":"66133267","content_type":"video","content_id":"1043309521","content_offset_seconds":810,"commenter":{"display_name":"frankz_071","_id":"615028132","name":"frankz_071","bio":null,"created_at":"2020-11-30T23:16:37.77627Z","updated_at":"2021-08-08T03:02:54.025912Z","logo":"https://static-cdn.jtvnw.net/user-default-pictures-uv/41780b5a-def8-11e9-94d9-784f43822e80-profile_image-300x300.png"},"message":{"body":"Hey do you use the Kilo?","bits_spent":0,"fragments":[{"text":"Hey do you use the Kilo?","emoticon":null}],"user_badges":[],"user_color":null,"emoticons":[]}},{"_id":"yrAmlB_ChBY5eg","created_at":"2021-06-02T12:00:04.9351617Z","channel_id":"66133267","content_type":"video","content_id":"1043309521","content_offset_seconds":834,"commenter":{"display_name":"Rocca017","_id":"195145656","name":"rocca017","bio":null,"created_at":"2018-02-07T01:14:37.608043Z","updated_at":"2024-03-12T16:30:24.177501Z","logo":"https://static-cdn.jtvnw.net/jtv_user_pictures/3ce9832e-9c4f-4c43-9853-f68f7787fcc9-profile_image-300x300.png"},"message":{"body":"yes to both","bits_spent":0,"fragments":[{"text":"yes to both","emoticon":null}],"user_badges":[{"_id":"moderator","version":"1"},{"_id":"subscriber","version":"6"},{"_id":"premium","version":"1"}],"user_color":"#693273","emoticons":[]}},{"_id":"sbomlB_ChBZacA","created_at":"2021-06-02T12:00:05.0402712Z","channel_id":"66133267","content_type":"video","content_id":"1043309521","content_offset_seconds":868,"commenter":{"display_name":"Rocca017","_id":"195145656","name":"rocca017","bio":null,"created_at":"2018-02-07T01:14:37.608043Z","updated_at":"2024-03-12T16:30:24.177501Z","logo":"https://static-cdn.jtvnw.net/jtv_user_pictures/3ce9832e-9c4f-4c43-9853-f68f7787fcc9-profile_image-300x300.png"},"message":{"body":"but he hasn't grinded the blue dot yet :)","bits_spent":0,"fragments":[{"text":"but he hasn't grinded the blue dot yet ","emoticon":null},{"text":":)","emoticon":{"emoticon_id":"1"}}],"user_badges":[{"_id":"moderator","version":"1"},{"_id":"subscriber","version":"6"},{"_id":"premium","version":"1"}],"user_color":"#693273","emoticons":[{"_id":"1","begin":39,"end":42}]}},{"_id":"WsUmlB_ChBbsKw","created_at":"2021-06-02T12:00:05.1649582Z","channel_id":"66133267","content_type":"video","content_id":"1043309521","content_offset_seconds":870,"commenter":{"display_name":"racsogorilla64","_id":"512574758","name":"racsogorilla64","bio":"Yo","created_at":"2020-04-11T20:06:28.842772Z","updated_at":"2024-03-07T22:01:25.606094Z","logo":"https://static-cdn.jtvnw.net/jtv_user_pictures/5e1ff04e-df52-4610-86fe-4c21075ed542-profile_image-300x300.png"},"message":{"body":"Yo Michiel keep up the good work from bboy_yoddha:)","bits_spent":0,"fragments":[{"text":"Yo Michiel keep up the good work from bboy_yoddha:)","emoticon":null}],"user_badges":[],"user_color":null,"emoticons":[]}},{"_id":"tw4nlB_ChBbxsg","created_at":"2021-06-02T12:00:05.2356422Z","channel_id":"66133267","content_type":"video","content_id":"1043309521","content_offset_seconds":881,"commenter":{"display_name":"frankz_071","_id":"615028132","name":"frankz_071","bio":null,"created_at":"2020-11-30T23:16:37.77627Z","updated_at":"2021-08-08T03:02:54.025912Z","logo":"https://static-cdn.jtvnw.net/user-default-pictures-uv/41780b5a-def8-11e9-94d9-784f43822e80-profile_image-300x300.png"},"message":{"body":"Yoo your popping off with the kar my guy","bits_spent":0,"fragments":[{"text":"Yoo your popping off with the kar my guy","emoticon":null}],"user_badges":[],"user_color":null,"emoticons":[]}},{"_id":"IxknlB_ChBbWxQ","created_at":"2021-06-02T12:00:05.2887969Z","channel_id":"66133267","content_type":"video","content_id":"1043309521","content_offset_seconds":910,"commenter":{"display_name":"drizzo_fn","_id":"693049921","name":"drizzo_fn","bio":null,"created_at":"2021-06-01T19:48:26.079088Z","updated_at":"2022-03-06T22:17:48.637437Z","logo":"https://static-cdn.jtvnw.net/user-default-pictures-uv/75305d54-c7cc-40d1-bb9c-91fbe85943c7-profile_image-300x300.png"},"message":{"body":"What’s your load out look like","bits_spent":0,"fragments":[{"text":"What’s your load out look like","emoticon":null}],"user_badges":[],"user_color":null,"emoticons":[]}},{"_id":"JiMnlB_ChBYlWw","created_at":"2021-06-02T12:00:05.3333156Z","channel_id":"66133267","content_type":"video","content_id":"1043309521","content_offset_seconds":913,"commenter":{"display_name":"loumoens","_id":"631617218","name":"loumoens","bio":null,"created_at":"2021-01-05T19:41:48.570158Z","updated_at":"2022-05-12T17:59:16.274538Z","logo":"https://static-cdn.jtvnw.net/user-default-pictures-uv/ebb84563-db81-4b9c-8940-64ed33ccfc7b-profile_image-300x300.png"},"message":{"body":"wall hacker","bits_spent":0,"fragments":[{"text":"wall hacker","emoticon":null}],"user_badges":[{"_id":"subscriber","version":"0"}],"user_color":null,"emoticons":[]}},{"_id":"Ky0nlB_ChBY7lw","created_at":"2021-06-02T12:00:05.3835615Z","channel_id":"66133267","content_type":"video","content_id":"1043309521","content_offset_seconds":923,"commenter":{"display_name":"Rocca017","_id":"195145656","name":"rocca017","bio":null,"created_at":"2018-02-07T01:14:37.608043Z","updated_at":"2024-03-12T16:30:24.177501Z","logo":"https://static-cdn.jtvnw.net/jtv_user_pictures/3ce9832e-9c4f-4c43-9853-f68f7787fcc9-profile_image-300x300.png"},"message":{"body":"!loadout","bits_spent":0,"fragments":[{"text":"!loadout","emoticon":null}],"user_badges":[{"_id":"moderator","version":"1"},{"_id":"subscriber","version":"6"},{"_id":"premium","version":"1"}],"user_color":"#693273","emoticons":[]}},{"_id":"-DYnlB_ChBZl0A","created_at":"2021-06-02T12:00:05.4225773Z","channel_id":"66133267","content_type":"video","content_id":"1043309521","content_offset_seconds":923,"commenter":{"display_name":"Nightbot","_id":"19264788","name":"nightbot","bio":"A chat moderation bot on Twitch. Visit nightbot.com to add Nightbot to your stream.","created_at":"2011-01-05T00:34:05.973707Z","updated_at":"2023-09-19T19:22:52.563766Z","logo":"https://static-cdn.jtvnw.net/jtv_user_pictures/nightbot-profile_image-2345338c09b4d468-300x300.png"},"message":{"body":"Here you can find Michiel's loadouts! https://docs.google.com/spreadsheets/d/1phx8qao7HLY6Da0YeUSjyfTgVQtdYSjg1eMwdoJjASM/edit?usp=sharing","bits_spent":0,"fragments":[{"text":"Here you can find Michiel's loadouts! ","emoticon":null},{"text":"https://docs.google.com/spreadsheets/d/1phx8qao7HLY6Da0YeUSjyfTgVQtdYSjg1eMwdoJjASM/edit?usp=sharing","emoticon":null}],"user_badges":[{"_id":"moderator","version":"1"},{"_id":"subscriber","version":"2"},{"_id":"partner","version":"1"}],"user_color":"#7C7CE1","emoticons":[]}},{"_id":"J0EnlB_ChBYZWA","created_at":"2021-06-02T12:00:05.5003521Z","channel_id":"66133267","content_type":"video","content_id":"1043309521","content_offset_seconds":929,"commenter":{"display_name":"elheenry","_id":"550555526","name":"elheenry","bio":"Hola, soy Henry y me gusta entretener y sacar una sonrisa\uD83D\uDE01","created_at":"2020-07-03T04:28:52.32938Z","updated_at":"2023-12-08T01:28:01.121778Z","logo":"https://static-cdn.jtvnw.net/jtv_user_pictures/e35e848f-51fb-43c0-9fe2-66922dd09aae-profile_image-300x300.png"},"message":{"body":"you have enough tattoos\uD83D\uDE2F\uD83D\uDE2F","bits_spent":0,"fragments":[{"text":"you have enough tattoos\uD83D\uDE2F\uD83D\uDE2F","emoticon":null}],"user_badges":[],"user_color":"#1E90FF","emoticons":[]}},{"_id":"p0snlB_ChBYmmQ","created_at":"2021-06-02T12:00:05.5482494Z","channel_id":"66133267","content_type":"video","content_id":"1043309521","content_offset_seconds":939,"commenter":{"display_name":"Rocca017","_id":"195145656","name":"rocca017","bio":null,"created_at":"2018-02-07T01:14:37.608043Z","updated_at":"2024-03-12T16:30:24.177501Z","logo":"https://static-cdn.jtvnw.net/jtv_user_pictures/3ce9832e-9c4f-4c43-9853-f68f7787fcc9-profile_image-300x300.png"},"message":{"body":"@loumoens denk het ni ;)","bits_spent":0,"fragments":[{"text":"@loumoens","emoticon":null},{"text":" denk het ni ","emoticon":null},{"text":";)","emoticon":{"emoticon_id":"555555589"}}],"user_badges":[{"_id":"moderator","version":"1"},{"_id":"subscriber","version":"6"},{"_id":"premium","version":"1"}],"user_color":"#693273","emoticons":[{"_id":"555555589","begin":22,"end":25}]}},{"_id":"N1YnlB_ChBZnbA","created_at":"2021-06-02T12:00:05.6101203Z","channel_id":"66133267","content_type":"video","content_id":"1043309521","content_offset_seconds":945,"commenter":{"display_name":"racsogorilla64","_id":"512574758","name":"racsogorilla64","bio":"Yo","created_at":"2020-04-11T20:06:28.842772Z","updated_at":"2024-03-07T22:01:25.606094Z","logo":"https://static-cdn.jtvnw.net/jtv_user_pictures/5e1ff04e-df52-4610-86fe-4c21075ed542-profile_image-300x300.png"},"message":{"body":"Yo you are the best dude!!!!","bits_spent":0,"fragments":[{"text":"Yo you are the best dude!!!!","emoticon":null}],"user_badges":[],"user_color":null,"emoticons":[]}},{"_id":"SWAnlB_ChBbjjA","created_at":"2021-06-02T12:00:05.6703341Z","channel_id":"66133267","content_type":"video","content_id":"1043309521","content_offset_seconds":968,"commenter":{"display_name":"benfaassen_","_id":"429639856","name":"benfaassen_","bio":null,"created_at":"2019-04-12T22:03:44.698924Z","updated_at":"2024-03-24T20:45:03.270518Z","logo":"https://static-cdn.jtvnw.net/user-default-pictures-uv/de130ab0-def7-11e9-b668-784f43822e80-profile_image-300x300.png"},"message":{"body":"michie2GulagKing michie2GulagKing michie2GulagKing","bits_spent":0,"fragments":[{"text":"michie2GulagKing","emoticon":{"emoticon_id":"305842138"}},{"text":" ","emoticon":null},{"text":"michie2GulagKing","emoticon":{"emoticon_id":"305842138"}},{"text":" ","emoticon":null},{"text":"michie2GulagKing","emoticon":{"emoticon_id":"305842138"}}],"user_badges":[{"_id":"subscriber","version":"6"},{"_id":"hype-train","version":"1"}],"user_color":"#FF0000","emoticons":[{"_id":"305842138","begin":0,"end":17},{"_id":"305842138","begin":17,"end":34},{"_id":"305842138","begin":34,"end":51}]}},{"_id":"tWonlB_ChBYevQ","created_at":"2021-06-02T12:00:05.7163615Z","channel_id":"66133267","content_type":"video","content_id":"1043309521","content_offset_seconds":971,"commenter":{"display_name":"loumoens","_id":"631617218","name":"loumoens","bio":null,"created_at":"2021-01-05T19:41:48.570158Z","updated_at":"2022-05-12T17:59:16.274538Z","logo":"https://static-cdn.jtvnw.net/user-default-pictures-uv/ebb84563-db81-4b9c-8940-64ed33ccfc7b-profile_image-300x300.png"},"message":{"body":"hij kan michiel ni zomaar killlen","bits_spent":0,"fragments":[{"text":"hij kan michiel ni zomaar killlen","emoticon":null}],"user_badges":[{"_id":"subscriber","version":"0"}],"user_color":null,"emoticons":[]}},{"_id":"6XQnlB_ChBbyHQ","created_at":"2021-06-02T12:00:05.839508Z","channel_id":"66133267","content_type":"video","content_id":"1043309521","content_offset_seconds":982,"commenter":{"display_name":"loumoens","_id":"631617218","name":"loumoens","bio":null,"created_at":"2021-01-05T19:41:48.570158Z","updated_at":"2022-05-12T17:59:16.274538Z","logo":"https://static-cdn.jtvnw.net/user-default-pictures-uv/ebb84563-db81-4b9c-8940-64ed33ccfc7b-profile_image-300x300.png"},"message":{"body":"wat een lul","bits_spent":0,"fragments":[{"text":"wat een lul","emoticon":null}],"user_badges":[{"_id":"subscriber","version":"0"}],"user_color":null,"emoticons":[]}},{"_id":"hn8nlB_ChBbbnA","created_at":"2021-06-02T12:00:05.8789748Z","channel_id":"66133267","content_type":"video","content_id":"1043309521","content_offset_seconds":983,"commenter":{"display_name":"frankz_071","_id":"615028132","name":"frankz_071","bio":null,"created_at":"2020-11-30T23:16:37.77627Z","updated_at":"2021-08-08T03:02:54.025912Z","logo":"https://static-cdn.jtvnw.net/user-default-pictures-uv/41780b5a-def8-11e9-94d9-784f43822e80-profile_image-300x300.png"},"message":{"body":"Do you do custom games?","bits_spent":0,"fragments":[{"text":"Do you do custom games?","emoticon":null}],"user_badges":[],"user_color":null,"emoticons":[]}},{"_id":"mIonlB_ChBYC4g","created_at":"2021-06-02T12:00:05.9075239Z","channel_id":"66133267","content_type":"video","content_id":"1043309521","content_offset_seconds":1000,"commenter":{"display_name":"シシシシシシシシシシシ","_id":"15439691","name":"fatstarl0rd","bio":"","created_at":"2010-09-10T22:17:59.278724Z","updated_at":"2024-04-01T21:40:29.763228Z","logo":"https://static-cdn.jtvnw.net/jtv_user_pictures/73482d9c-b2d2-49d6-a7fa-dde1abdca150-profile_image-300x300.png"},"message":{"body":"@frankz_071 Sunday 4pm CET","bits_spent":0,"fragments":[{"text":"@frankz_071","emoticon":null},{"text":" Sunday 4pm CET","emoticon":null}],"user_badges":[{"_id":"moderator","version":"1"},{"_id":"subscriber","version":"3"},{"_id":"premium","version":"1"}],"user_color":"#FF69B4","emoticons":[]}},{"_id":"BJYnlB_ChBYw3g","created_at":"2021-06-02T12:00:05.9572787Z","channel_id":"66133267","content_type":"video","content_id":"1043309521","content_offset_seconds":1005,"commenter":{"display_name":"drizzo_fn","_id":"693049921","name":"drizzo_fn","bio":null,"created_at":"2021-06-01T19:48:26.079088Z","updated_at":"2022-03-06T22:17:48.637437Z","logo":"https://static-cdn.jtvnw.net/user-default-pictures-uv/75305d54-c7cc-40d1-bb9c-91fbe85943c7-profile_image-300x300.png"},"message":{"body":"How do you get the t pose crosshair","bits_spent":0,"fragments":[{"text":"How do you get the t pose crosshair","emoticon":null}],"user_badges":[],"user_color":null,"emoticons":[]}},{"_id":"nqAnlB_ChBa0Qw","created_at":"2021-06-02T12:00:06.0084812Z","channel_id":"66133267","content_type":"video","content_id":"1043309521","content_offset_seconds":1032,"commenter":{"display_name":"Rocca017","_id":"195145656","name":"rocca017","bio":null,"created_at":"2018-02-07T01:14:37.608043Z","updated_at":"2024-03-12T16:30:24.177501Z","logo":"https://static-cdn.jtvnw.net/jtv_user_pictures/3ce9832e-9c4f-4c43-9853-f68f7787fcc9-profile_image-300x300.png"},"message":{"body":"@drizzo_fn i think google has the anwser","bits_spent":0,"fragments":[{"text":"@drizzo_fn","emoticon":null},{"text":" i think google has the anwser","emoticon":null}],"user_badges":[{"_id":"moderator","version":"1"},{"_id":"subscriber","version":"6"},{"_id":"premium","version":"1"}],"user_color":"#693273","emoticons":[]}},{"_id":"6qonlB_ChBb3FQ","created_at":"2021-06-02T12:00:06.063989Z","channel_id":"66133267","content_type":"video","content_id":"1043309521","content_offset_seconds":1036,"commenter":{"display_name":"frankz_071","_id":"615028132","name":"frankz_071","bio":null,"created_at":"2020-11-30T23:16:37.77627Z","updated_at":"2021-08-08T03:02:54.025912Z","logo":"https://static-cdn.jtvnw.net/user-default-pictures-uv/41780b5a-def8-11e9-94d9-784f43822e80-profile_image-300x300.png"},"message":{"body":"Oh thx @fatstarlord_","bits_spent":0,"fragments":[{"text":"Oh thx ","emoticon":null},{"text":"@fatstarlord_","emoticon":null}],"user_badges":[],"user_color":null,"emoticons":[]}},{"_id":"JbYnlB_ChBa_DA","created_at":"2021-06-02T12:00:06.1125638Z","channel_id":"66133267","content_type":"video","content_id":"1043309521","content_offset_seconds":1038,"commenter":{"display_name":"elheenry","_id":"550555526","name":"elheenry","bio":"Hola, soy Henry y me gusta entretener y sacar una sonrisa\uD83D\uDE01","created_at":"2020-07-03T04:28:52.32938Z","updated_at":"2023-12-08T01:28:01.121778Z","logo":"https://static-cdn.jtvnw.net/jtv_user_pictures/e35e848f-51fb-43c0-9fe2-66922dd09aae-profile_image-300x300.png"},"message":{"body":"Hola amigo\uD83E\uDD70","bits_spent":0,"fragments":[{"text":"Hola amigo\uD83E\uDD70","emoticon":null}],"user_badges":[],"user_color":"#1E90FF","emoticons":[]}},{"_id":"D8EnlB_ChBYQeQ","created_at":"2021-06-02T12:00:06.1485732Z","channel_id":"66133267","content_type":"video","content_id":"1043309521","content_offset_seconds":1056,"commenter":{"display_name":"racsogorilla64","_id":"512574758","name":"racsogorilla64","bio":"Yo","created_at":"2020-04-11T20:06:28.842772Z","updated_at":"2024-03-07T22:01:25.606094Z","logo":"https://static-cdn.jtvnw.net/jtv_user_pictures/5e1ff04e-df52-4610-86fe-4c21075ed542-profile_image-300x300.png"},"message":{"body":"Which headset do you use??","bits_spent":0,"fragments":[{"text":"Which headset do you use??","emoticon":null}],"user_badges":[],"user_color":null,"emoticons":[]}},{"_id":"vssnlB_ChBYtlQ","created_at":"2021-06-02T12:00:06.1956061Z","channel_id":"66133267","content_type":"video","content_id":"1043309521","content_offset_seconds":1066,"commenter":{"display_name":"Rocca017","_id":"195145656","name":"rocca017","bio":null,"created_at":"2018-02-07T01:14:37.608043Z","updated_at":"2024-03-12T16:30:24.177501Z","logo":"https://static-cdn.jtvnw.net/jtv_user_pictures/3ce9832e-9c4f-4c43-9853-f68f7787fcc9-profile_image-300x300.png"},"message":{"body":"!headset","bits_spent":0,"fragments":[{"text":"!headset","emoticon":null}],"user_badges":[{"_id":"moderator","version":"1"},{"_id":"subscriber","version":"6"},{"_id":"premium","version":"1"}],"user_color":"#693273","emoticons":[]}},{"_id":"4tUnlB_ChBZIXA","created_at":"2021-06-02T12:00:06.2344301Z","channel_id":"66133267","content_type":"video","content_id":"1043309521","content_offset_seconds":1066,"commenter":{"display_name":"Nightbot","_id":"19264788","name":"nightbot","bio":"A chat moderation bot on Twitch. Visit nightbot.com to add Nightbot to your stream.","created_at":"2011-01-05T00:34:05.973707Z","updated_at":"2023-09-19T19:22:52.563766Z","logo":"https://static-cdn.jtvnw.net/jtv_user_pictures/nightbot-profile_image-2345338c09b4d468-300x300.png"},"message":{"body":"Michiel uses the Beyerdynamic DT990 Pro 250 ohm with a GoXLR","bits_spent":0,"fragments":[{"text":"Michiel uses the Beyerdynamic DT990 Pro 250 ohm with a GoXLR","emoticon":null}],"user_badges":[{"_id":"moderator","version":"1"},{"_id":"subscriber","version":"2"},{"_id":"partner","version":"1"}],"user_color":"#7C7CE1","emoticons":[]}},{"_id":"AuAnlB_ChBa_nQ","created_at":"2021-06-02T12:00:06.3649385Z","channel_id":"66133267","content_type":"video","content_id":"1043309521","content_offset_seconds":1068,"commenter":{"display_name":"aldoz120","_id":"491703266","name":"aldoz120","bio":"dude that's tryna make it out the hood","created_at":"2020-02-10T21:39:44.180558Z","updated_at":"2024-02-11T03:46:43.385327Z","logo":"https://static-cdn.jtvnw.net/user-default-pictures-uv/294c98b5-e34d-42cd-a8f0-140b72fba9b0-profile_image-300x300.png"},"message":{"body":"Hello","bits_spent":0,"fragments":[{"text":"Hello","emoticon":null}],"user_badges":[],"user_color":null,"emoticons":[]}},{"_id":"zuonlB_ChBa-OA","created_at":"2021-06-02T12:00:06.4117984Z","channel_id":"66133267","content_type":"video","content_id":"1043309521","content_offset_seconds":1082,"commenter":{"display_name":"racsogorilla64","_id":"512574758","name":"racsogorilla64","bio":"Yo","created_at":"2020-04-11T20:06:28.842772Z","updated_at":"2024-03-07T22:01:25.606094Z","logo":"https://static-cdn.jtvnw.net/jtv_user_pictures/5e1ff04e-df52-4610-86fe-4c21075ed542-profile_image-300x300.png"},"message":{"body":"Thanks bro","bits_spent":0,"fragments":[{"text":"Thanks bro","emoticon":null}],"user_badges":[],"user_color":null,"emoticons":[]}},{"_id":"2vQnlB_ChBYLPw","created_at":"2021-06-02T12:00:06.4534477Z","channel_id":"66133267","content_type":"video","content_id":"1043309521","content_offset_seconds":1088,"commenter":{"display_name":"Rocca017","_id":"195145656","name":"rocca017","bio":null,"created_at":"2018-02-07T01:14:37.608043Z","updated_at":"2024-03-12T16:30:24.177501Z","logo":"https://static-cdn.jtvnw.net/jtv_user_pictures/3ce9832e-9c4f-4c43-9853-f68f7787fcc9-profile_image-300x300.png"},"message":{"body":"@MichielVandeweert ge hebt de verkeerde loadout niet :D ge hebt Specialist :D","bits_spent":0,"fragments":[{"text":"@MichielVandeweert","emoticon":null},{"text":" ge hebt de verkeerde loadout niet ","emoticon":null},{"text":":D","emoticon":{"emoticon_id":"555555560"}},{"text":" ge hebt Specialist ","emoticon":null},{"text":":D","emoticon":{"emoticon_id":"555555560"}}],"user_badges":[{"_id":"moderator","version":"1"},{"_id":"subscriber","version":"6"},{"_id":"premium","version":"1"}],"user_color":"#693273","emoticons":[{"_id":"555555560","begin":53,"end":56},{"_id":"555555560","begin":75,"end":78}]}},{"_id":"NgQolB_ChBa4tg","created_at":"2021-06-02T12:00:06.5266012Z","channel_id":"66133267","content_type":"video","content_id":"1043309521","content_offset_seconds":1094,"commenter":{"display_name":"racsogorilla64","_id":"512574758","name":"racsogorilla64","bio":"Yo","created_at":"2020-04-11T20:06:28.842772Z","updated_at":"2024-03-07T22:01:25.606094Z","logo":"https://static-cdn.jtvnw.net/jtv_user_pictures/5e1ff04e-df52-4610-86fe-4c21075ed542-profile_image-300x300.png"},"message":{"body":"Even tho it’s s bot","bits_spent":0,"fragments":[{"text":"Even tho it’s s bot","emoticon":null}],"user_badges":[],"user_color":null,"emoticons":[]}},{"_id":"qg4olB_ChBa9vw","created_at":"2021-06-02T12:00:06.6098001Z","channel_id":"66133267","content_type":"video","content_id":"1043309521","content_offset_seconds":1096,"commenter":{"display_name":"cool_aaron123","_id":"625308338","name":"cool_aaron123","bio":null,"created_at":"2020-12-24T05:40:43.687595Z","updated_at":"2022-08-20T01:26:44.773672Z","logo":"https://static-cdn.jtvnw.net/jtv_user_pictures/b48557ad-b010-4910-b7aa-57680a842cc4-profile_image-300x300.png"},"message":{"body":"Yo","bits_spent":0,"fragments":[{"text":"Yo","emoticon":null}],"user_badges":[],"user_color":null,"emoticons":[]}},{"_id":"LXp_FSDChBYb_Q","created_at":"2021-06-02T12:00:06.7153886Z","channel_id":"66133267","content_type":"video","content_id":"1043309521","content_offset_seconds":1100,"commenter":{"display_name":"racsogorilla64","_id":"512574758","name":"racsogorilla64","bio":"Yo","created_at":"2020-04-11T20:06:28.842772Z","updated_at":"2024-03-07T22:01:25.606094Z","logo":"https://static-cdn.jtvnw.net/jtv_user_pictures/5e1ff04e-df52-4610-86fe-4c21075ed542-profile_image-300x300.png"},"message":{"body":"Yo","bits_spent":0,"fragments":[{"text":"Yo","emoticon":null}],"user_badges":[],"user_color":null,"emoticons":[]}},{"_id":"5Yx_FSDChBZXrA","created_at":"2021-06-02T12:00:06.7560776Z","channel_id":"66133267","content_type":"video","content_id":"1043309521","content_offset_seconds":1104,"commenter":{"display_name":"cool_aaron123","_id":"625308338","name":"cool_aaron123","bio":null,"created_at":"2020-12-24T05:40:43.687595Z","updated_at":"2022-08-20T01:26:44.773672Z","logo":"https://static-cdn.jtvnw.net/jtv_user_pictures/b48557ad-b010-4910-b7aa-57680a842cc4-profile_image-300x300.png"},"message":{"body":"DoritosChip","bits_spent":0,"fragments":[{"text":"DoritosChip","emoticon":{"emoticon_id":"102242"}}],"user_badges":[],"user_color":null,"emoticons":[{"_id":"102242","begin":0,"end":12}]}},{"_id":"cJh_FSDChBZmZg","created_at":"2021-06-02T12:00:06.7926861Z","channel_id":"66133267","content_type":"video","content_id":"1043309521","content_offset_seconds":1110,"commenter":{"display_name":"munkadojofiddelyoyo","_id":"44580101","name":"munkadojofiddelyoyo","bio":"","created_at":"2013-06-10T15:19:35.209355Z","updated_at":"2024-04-01T12:55:01.706289Z","logo":"https://static-cdn.jtvnw.net/user-default-pictures-uv/ce57700a-def9-11e9-842d-784f43822e80-profile_image-300x300.png"},"message":{"body":"süuup","bits_spent":0,"fragments":[{"text":"süuup","emoticon":null}],"user_badges":[{"_id":"subscriber","version":"0"}],"user_color":"#008000","emoticons":[]}},{"_id":"LKR_FSDChBbQJQ","created_at":"2021-06-02T12:00:06.8350364Z","channel_id":"66133267","content_type":"video","content_id":"1043309521","content_offset_seconds":1182,"commenter":{"display_name":"akswim022","_id":"193418916","name":"akswim022","bio":null,"created_at":"2018-01-28T01:41:53.555188Z","updated_at":"2023-08-30T00:51:01.141362Z","logo":"https://static-cdn.jtvnw.net/user-default-pictures-uv/294c98b5-e34d-42cd-a8f0-140b72fba9b0-profile_image-300x300.png"},"message":{"body":"yo","bits_spent":0,"fragments":[{"text":"yo","emoticon":null}],"user_badges":[],"user_color":null,"emoticons":[]}},{"_id":"b69_FSDChBbd0g","created_at":"2021-06-02T12:00:06.8742153Z","channel_id":"66133267","content_type":"video","content_id":"1043309521","content_offset_seconds":1188,"commenter":{"display_name":"Rocca017","_id":"195145656","name":"rocca017","bio":null,"created_at":"2018-02-07T01:14:37.608043Z","updated_at":"2024-03-12T16:30:24.177501Z","logo":"https://static-cdn.jtvnw.net/jtv_user_pictures/3ce9832e-9c4f-4c43-9853-f68f7787fcc9-profile_image-300x300.png"},"message":{"body":"!focus","bits_spent":0,"fragments":[{"text":"!focus","emoticon":null}],"user_badges":[{"_id":"moderator","version":"1"},{"_id":"subscriber","version":"6"},{"_id":"premium","version":"1"}],"user_color":"#693273","emoticons":[]}},{"_id":"dbp_FSDChBaD8A","created_at":"2021-06-02T12:00:06.9168502Z","channel_id":"66133267","content_type":"video","content_id":"1043309521","content_offset_seconds":1188,"commenter":{"display_name":"Nightbot","_id":"19264788","name":"nightbot","bio":"A chat moderation bot on Twitch. Visit nightbot.com to add Nightbot to your stream.","created_at":"2011-01-05T00:34:05.973707Z","updated_at":"2023-09-19T19:22:52.563766Z","logo":"https://static-cdn.jtvnw.net/jtv_user_pictures/nightbot-profile_image-2345338c09b4d468-300x300.png"},"message":{"body":"Michiel is locked in right now, he'll answer your questions when there is a calm moment in game! Michiel is super gefocust momenteel, hij zal jullie vragen beantwoorden tijdens een rustiger moment in de game!","bits_spent":0,"fragments":[{"text":"Michiel is locked in right now, he'll answer your questions when there is a calm moment in game! Michiel is super gefocust momenteel, hij zal jullie vragen beantwoorden tijdens een rustiger moment in de game!","emoticon":null}],"user_badges":[{"_id":"moderator","version":"1"},{"_id":"subscriber","version":"2"},{"_id":"partner","version":"1"}],"user_color":"#7C7CE1","emoticons":[]}},{"_id":"1sR_FSDChBaUvA","created_at":"2021-06-02T12:00:07.0201628Z","channel_id":"66133267","content_type":"video","content_id":"1043309521","content_offset_seconds":1195,"commenter":{"display_name":"Nightbot","_id":"19264788","name":"nightbot","bio":"A chat moderation bot on Twitch. Visit nightbot.com to add Nightbot to your stream.","created_at":"2011-01-05T00:34:05.973707Z","updated_at":"2023-09-19T19:22:52.563766Z","logo":"https://static-cdn.jtvnw.net/jtv_user_pictures/nightbot-profile_image-2345338c09b4d468-300x300.png"},"message":{"body":"@mrsandman694200 -> My name is Michiel just call me that :) [warning]","bits_spent":0,"fragments":[{"text":"@mrsandman694200","emoticon":null},{"text":" -> My name is Michiel just call me that ","emoticon":null},{"text":":)","emoticon":{"emoticon_id":"499"}},{"text":" [warning]","emoticon":null}],"user_badges":[{"_id":"moderator","version":"1"},{"_id":"subscriber","version":"2"},{"_id":"partner","version":"1"}],"user_color":"#7C7CE1","emoticons":[{"_id":"499","begin":57,"end":60}]}},{"_id":"jNB_FSDChBYC5Q","created_at":"2021-06-02T12:00:07.0806902Z","channel_id":"66133267","content_type":"video","content_id":"1043309521","content_offset_seconds":1206,"commenter":{"display_name":"mrsandman694200","_id":"610840635","name":"mrsandman694200","bio":null,"created_at":"2020-11-19T20:39:05.470214Z","updated_at":"2021-05-31T23:42:15.142882Z","logo":"https://static-cdn.jtvnw.net/user-default-pictures-uv/294c98b5-e34d-42cd-a8f0-140b72fba9b0-profile_image-300x300.png"},"message":{"body":"No","bits_spent":0,"fragments":[{"text":"No","emoticon":null}],"user_badges":[],"user_color":null,"emoticons":[]}},{"_id":"j9t_FSDChBaFYA","created_at":"2021-06-02T12:00:07.1380143Z","channel_id":"66133267","content_type":"video","content_id":"1043309521","content_offset_seconds":1212,"commenter":{"display_name":"notyep_spelled_backwards","_id":"425875244","name":"notyep_spelled_backwards","bio":"Come watch ","created_at":"2019-03-25T21:34:18.015494Z","updated_at":"2024-03-24T02:09:16.256551Z","logo":"https://static-cdn.jtvnw.net/jtv_user_pictures/c4ee3916-c2bf-41ff-93de-71b4d028064b-profile_image-300x300.png"},"message":{"body":"Rd","bits_spent":0,"fragments":[{"text":"Rd","emoticon":null}],"user_badges":[],"user_color":null,"emoticons":[]}},{"_id":"0-Z_FSDChBb8Uw","created_at":"2021-06-02T12:00:07.1782367Z","channel_id":"66133267","content_type":"video","content_id":"1043309521","content_offset_seconds":1231,"commenter":{"display_name":"notyep_spelled_backwards","_id":"425875244","name":"notyep_spelled_backwards","bio":"Come watch ","created_at":"2019-03-25T21:34:18.015494Z","updated_at":"2024-03-24T02:09:16.256551Z","logo":"https://static-cdn.jtvnw.net/jtv_user_pictures/c4ee3916-c2bf-41ff-93de-71b4d028064b-profile_image-300x300.png"},"message":{"body":"Tuff ass skin on that gun","bits_spent":0,"fragments":[{"text":"Tuff ass skin on that gun","emoticon":null}],"user_badges":[],"user_color":null,"emoticons":[]}},{"_id":"K_1_FSDChBY_kg","created_at":"2021-06-02T12:00:07.2207044Z","channel_id":"66133267","content_type":"video","content_id":"1043309521","content_offset_seconds":1286,"commenter":{"display_name":"Nightbot","_id":"19264788","name":"nightbot","bio":"A chat moderation bot on Twitch. Visit nightbot.com to add Nightbot to your stream.","created_at":"2011-01-05T00:34:05.973707Z","updated_at":"2023-09-19T19:22:52.563766Z","logo":"https://static-cdn.jtvnw.net/jtv_user_pictures/nightbot-profile_image-2345338c09b4d468-300x300.png"},"message":{"body":"I drink Guice Energy during my streams! I'm always feeling tired, but Guice gives me that energy to stream everyday, it's honestly an amazing product! Use my code: Michiel for 15% off https://guiceenergy.eu/","bits_spent":0,"fragments":[{"text":"I drink Guice Energy during my streams! I'm always feeling tired, but Guice gives me that energy to stream everyday, it's honestly an amazing product! Use my code: Michiel for 15% off ","emoticon":null},{"text":"https://guiceenergy.eu/","emoticon":null}],"user_badges":[{"_id":"moderator","version":"1"},{"_id":"subscriber","version":"2"},{"_id":"partner","version":"1"}],"user_color":"#7C7CE1","emoticons":[]}},{"_id":"RQiAFSDChBarUA","created_at":"2021-06-02T12:00:07.3124062Z","channel_id":"66133267","content_type":"video","content_id":"1043309521","content_offset_seconds":1300,"commenter":{"display_name":"Vlemety","_id":"644238356","name":"vlemety","bio":"Welkom op Vlemety. Mijn naam is Dean en ik maak onder anderen Live stream's Bijna dagelijks kan je een Live stream's van mij verwachten in zoetsappige 1080 HD kwaliteit. Ben je nieuw hier en wil je op de hoogte blijven van alles wat ik doe, dan kan je op de 'Volgen'-knop drukken.","created_at":"2021-01-31T16:18:40.143313Z","updated_at":"2024-04-01T16:12:27.509815Z","logo":"https://static-cdn.jtvnw.net/jtv_user_pictures/37bff007-35df-45b2-9d86-9c4bd1833b36-profile_image-300x300.png"},"message":{"body":"hoi hoe is het","bits_spent":0,"fragments":[{"text":"hoi hoe is het","emoticon":null}],"user_badges":[],"user_color":null,"emoticons":[]}},{"_id":"fxOAFSDChBaijw","created_at":"2021-06-02T12:00:07.3833655Z","channel_id":"66133267","content_type":"video","content_id":"1043309521","content_offset_seconds":1327,"commenter":{"display_name":"drizzo_fn","_id":"693049921","name":"drizzo_fn","bio":null,"created_at":"2021-06-01T19:48:26.079088Z","updated_at":"2022-03-06T22:17:48.637437Z","logo":"https://static-cdn.jtvnw.net/user-default-pictures-uv/75305d54-c7cc-40d1-bb9c-91fbe85943c7-profile_image-300x300.png"},"message":{"body":"U are good","bits_spent":0,"fragments":[{"text":"U are good","emoticon":null}],"user_badges":[],"user_color":null,"emoticons":[]}},{"_id":"Yx6AFSDChBaEsg","created_at":"2021-06-02T12:00:07.4321987Z","channel_id":"66133267","content_type":"video","content_id":"1043309521","content_offset_seconds":1333,"commenter":{"display_name":"Nightbot","_id":"19264788","name":"nightbot","bio":"A chat moderation bot on Twitch. Visit nightbot.com to add Nightbot to your stream.","created_at":"2011-01-05T00:34:05.973707Z","updated_at":"2023-09-19T19:22:52.563766Z","logo":"https://static-cdn.jtvnw.net/jtv_user_pictures/nightbot-profile_image-2345338c09b4d468-300x300.png"},"message":{"body":"follow all my socials here! https://linktr.ee/MichielVandeweert","bits_spent":0,"fragments":[{"text":"follow all my socials here! ","emoticon":null},{"text":"https://linktr.ee/MichielVandeweert","emoticon":null}],"user_badges":[{"_id":"moderator","version":"1"},{"_id":"subscriber","version":"2"},{"_id":"partner","version":"1"}],"user_color":"#7C7CE1","emoticons":[]}},{"_id":"TymAFSDChBb4jA","created_at":"2021-06-02T12:00:07.4735645Z","channel_id":"66133267","content_type":"video","content_id":"1043309521","content_offset_seconds":1355,"commenter":{"display_name":"Vlemety","_id":"644238356","name":"vlemety","bio":"Welkom op Vlemety. Mijn naam is Dean en ik maak onder anderen Live stream's Bijna dagelijks kan je een Live stream's van mij verwachten in zoetsappige 1080 HD kwaliteit. Ben je nieuw hier en wil je op de hoogte blijven van alles wat ik doe, dan kan je op de 'Volgen'-knop drukken.","created_at":"2021-01-31T16:18:40.143313Z","updated_at":"2024-04-01T16:12:27.509815Z","logo":"https://static-cdn.jtvnw.net/jtv_user_pictures/37bff007-35df-45b2-9d86-9c4bd1833b36-profile_image-300x300.png"},"message":{"body":"hoe is het","bits_spent":0,"fragments":[{"text":"hoe is het","emoticon":null}],"user_badges":[],"user_color":null,"emoticons":[]}},{"_id":"zTOAFSDChBapiA","created_at":"2021-06-02T12:00:07.5027296Z","channel_id":"66133267","content_type":"video","content_id":"1043309521","content_offset_seconds":1364,"commenter":{"display_name":"siemenswek","_id":"74532248","name":"siemenswek","bio":"DAG, Ik ben Siemen, 23, software tester en fervent gamer. ik ben weliswaar dogwater in elke game die ik speel maar ben de beste entertainer ter wereld (van mijn huis)","created_at":"2014-11-05T14:25:08.031979Z","updated_at":"2024-04-01T11:44:06.480947Z","logo":"https://static-cdn.jtvnw.net/jtv_user_pictures/759a58ab-1907-4387-b7b0-65b026646281-profile_image-300x300.jpeg"},"message":{"body":"de man heeft geld joh","bits_spent":0,"fragments":[{"text":"de man heeft geld joh","emoticon":null}],"user_badges":[{"_id":"moderator","version":"1"}],"user_color":"#FF69B4","emoticons":[]}},{"_id":"tT6AFSDChBavSQ","created_at":"2021-06-02T12:00:07.5525572Z","channel_id":"66133267","content_type":"video","content_id":"1043309521","content_offset_seconds":1368,"commenter":{"display_name":"Rocca017","_id":"195145656","name":"rocca017","bio":null,"created_at":"2018-02-07T01:14:37.608043Z","updated_at":"2024-03-12T16:30:24.177501Z","logo":"https://static-cdn.jtvnw.net/jtv_user_pictures/3ce9832e-9c4f-4c43-9853-f68f7787fcc9-profile_image-300x300.png"},"message":{"body":"!loadout","bits_spent":0,"fragments":[{"text":"!loadout","emoticon":null}],"user_badges":[{"_id":"moderator","version":"1"},{"_id":"subscriber","version":"6"},{"_id":"premium","version":"1"}],"user_color":"#693273","emoticons":[]}},{"_id":"o0mAFSDChBaksQ","created_at":"2021-06-02T12:00:07.5975686Z","channel_id":"66133267","content_type":"video","content_id":"1043309521","content_offset_seconds":1368,"commenter":{"display_name":"Nightbot","_id":"19264788","name":"nightbot","bio":"A chat moderation bot on Twitch. Visit nightbot.com to add Nightbot to your stream.","created_at":"2011-01-05T00:34:05.973707Z","updated_at":"2023-09-19T19:22:52.563766Z","logo":"https://static-cdn.jtvnw.net/jtv_user_pictures/nightbot-profile_image-2345338c09b4d468-300x300.png"},"message":{"body":"Here you can find Michiel's loadouts! https://docs.google.com/spreadsheets/d/1phx8qao7HLY6Da0YeUSjyfTgVQtdYSjg1eMwdoJjASM/edit?usp=sharing","bits_spent":0,"fragments":[{"text":"Here you can find Michiel's loadouts! ","emoticon":null},{"text":"https://docs.google.com/spreadsheets/d/1phx8qao7HLY6Da0YeUSjyfTgVQtdYSjg1eMwdoJjASM/edit?usp=sharing","emoticon":null}],"user_badges":[{"_id":"moderator","version":"1"},{"_id":"subscriber","version":"2"},{"_id":"partner","version":"1"}],"user_color":"#7C7CE1","emoticons":[]}},{"_id":"sFSAFSDChBboYQ","created_at":"2021-06-02T12:00:07.6343492Z","channel_id":"66133267","content_type":"video","content_id":"1043309521","content_offset_seconds":1384,"commenter":{"display_name":"Rocca017","_id":"195145656","name":"rocca017","bio":null,"created_at":"2018-02-07T01:14:37.608043Z","updated_at":"2024-03-12T16:30:24.177501Z","logo":"https://static-cdn.jtvnw.net/jtv_user_pictures/3ce9832e-9c4f-4c43-9853-f68f7787fcc9-profile_image-300x300.png"},"message":{"body":"@siemenswek ali is geleaved ... niet moeten terug kopen :D","bits_spent":0,"fragments":[{"text":"@siemenswek","emoticon":null},{"text":" ali is geleaved ... niet moeten terug kopen ","emoticon":null},{"text":":D","emoticon":{"emoticon_id":"555555560"}}],"user_badges":[{"_id":"moderator","version":"1"},{"_id":"subscriber","version":"6"},{"_id":"premium","version":"1"}],"user_color":"#693273","emoticons":[{"_id":"555555560","begin":56,"end":59}]}},{"_id":"3V6AFSDChBbUZw","created_at":"2021-06-02T12:00:07.6983748Z","channel_id":"66133267","content_type":"video","content_id":"1043309521","content_offset_seconds":1391,"commenter":{"display_name":"daqi_i","_id":"641846628","name":"daqi_i","bio":null,"created_at":"2021-01-26T20:28:55.937931Z","updated_at":"2024-01-28T21:42:06.390203Z","logo":"https://static-cdn.jtvnw.net/user-default-pictures-uv/ce57700a-def9-11e9-842d-784f43822e80-profile_image-300x300.png"},"message":{"body":"Vind ge Xbox controller chiller als ps controller","bits_spent":0,"fragments":[{"text":"Vind ge Xbox controller chiller als ps controller","emoticon":null}],"user_badges":[{"_id":"subscriber","version":"3"},{"_id":"sub-gift-leader","version":"1"}],"user_color":"#FF0000","emoticons":[]}},{"_id":"5WmAFSDChBZa3g","created_at":"2021-06-02T12:00:07.7835117Z","channel_id":"66133267","content_type":"video","content_id":"1043309521","content_offset_seconds":1411,"commenter":{"display_name":"iamaprincess2","_id":"543182709","name":"iamaprincess2","bio":null,"created_at":"2020-06-13T15:54:25.41111Z","updated_at":"2024-03-26T19:14:45.909137Z","logo":"https://static-cdn.jtvnw.net/user-default-pictures-uv/41780b5a-def8-11e9-94d9-784f43822e80-profile_image-300x300.png"},"message":{"body":"@Rocca017 lief zijn aub heb een mindere dag","bits_spent":0,"fragments":[{"text":"@Rocca017","emoticon":null},{"text":" lief zijn aub heb een mindere dag","emoticon":null}],"user_badges":[{"_id":"moderator","version":"1"},{"_id":"subscriber","version":"3"}],"user_color":"#FF69B4","emoticons":[]}},{"_id":"yHSAFSDChBbKMQ","created_at":"2021-06-02T12:00:07.8420368Z","channel_id":"66133267","content_type":"video","content_id":"1043309521","content_offset_seconds":1451,"commenter":{"display_name":"Nightbot","_id":"19264788","name":"nightbot","bio":"A chat moderation bot on Twitch. Visit nightbot.com to add Nightbot to your stream.","created_at":"2011-01-05T00:34:05.973707Z","updated_at":"2023-09-19T19:22:52.563766Z","logo":"https://static-cdn.jtvnw.net/jtv_user_pictures/nightbot-profile_image-2345338c09b4d468-300x300.png"},"message":{"body":"have you seen my latest youtube video yet? NO? go watch it then!! https://www.youtube.com/watch?v=AkdL2AGDzPM","bits_spent":0,"fragments":[{"text":"have you seen my latest youtube video yet? NO? go watch it then!! ","emoticon":null},{"text":"https://www.youtube.com/watch?v=AkdL2AGDzPM","emoticon":null}],"user_badges":[{"_id":"moderator","version":"1"},{"_id":"subscriber","version":"2"},{"_id":"partner","version":"1"}],"user_color":"#7C7CE1","emoticons":[]}},{"_id":"23-AFSDChBa4CA","created_at":"2021-06-02T12:00:07.8811857Z","channel_id":"66133267","content_type":"video","content_id":"1043309521","content_offset_seconds":1469,"commenter":{"display_name":"Rocca017","_id":"195145656","name":"rocca017","bio":null,"created_at":"2018-02-07T01:14:37.608043Z","updated_at":"2024-03-12T16:30:24.177501Z","logo":"https://static-cdn.jtvnw.net/jtv_user_pictures/3ce9832e-9c4f-4c43-9853-f68f7787fcc9-profile_image-300x300.png"},"message":{"body":"wtf gebuikt deze man op zijn amax :D","bits_spent":0,"fragments":[{"text":"wtf gebuikt deze man op zijn amax ","emoticon":null},{"text":":D","emoticon":{"emoticon_id":"555555560"}}],"user_badges":[{"_id":"moderator","version":"1"},{"_id":"subscriber","version":"6"},{"_id":"premium","version":"1"}],"user_color":"#693273","emoticons":[{"_id":"555555560","begin":34,"end":37}]}},{"_id":"GYqAFSDChBYu-g","created_at":"2021-06-02T12:00:07.9411538Z","channel_id":"66133267","content_type":"video","content_id":"1043309521","content_offset_seconds":1475,"commenter":{"display_name":"siemenswek","_id":"74532248","name":"siemenswek","bio":"DAG, Ik ben Siemen, 23, software tester en fervent gamer. ik ben weliswaar dogwater in elke game die ik speel maar ben de beste entertainer ter wereld (van mijn huis)","created_at":"2014-11-05T14:25:08.031979Z","updated_at":"2024-04-01T11:44:06.480947Z","logo":"https://static-cdn.jtvnw.net/jtv_user_pictures/759a58ab-1907-4387-b7b0-65b026646281-profile_image-300x300.jpeg"},"message":{"body":"@iamaprincess2 waskeburt","bits_spent":0,"fragments":[{"text":"@iamaprincess2","emoticon":null},{"text":" waskeburt","emoticon":null}],"user_badges":[{"_id":"moderator","version":"1"}],"user_color":"#FF69B4","emoticons":[]}},{"_id":"z5SAFSDChBZdVg","created_at":"2021-06-02T12:00:08.0034132Z","channel_id":"66133267","content_type":"video","content_id":"1043309521","content_offset_seconds":1478,"commenter":{"display_name":"loumoens","_id":"631617218","name":"loumoens","bio":null,"created_at":"2021-01-05T19:41:48.570158Z","updated_at":"2022-05-12T17:59:16.274538Z","logo":"https://static-cdn.jtvnw.net/user-default-pictures-uv/ebb84563-db81-4b9c-8940-64ed33ccfc7b-profile_image-300x300.png"},"message":{"body":"vlk is toch veel chiller dan deze","bits_spent":0,"fragments":[{"text":"vlk is toch veel chiller dan deze","emoticon":null}],"user_badges":[{"_id":"subscriber","version":"0"}],"user_color":null,"emoticons":[]}},{"_id":"MZ-AFSDChBaVKw","created_at":"2021-06-02T12:00:08.0500101Z","channel_id":"66133267","content_type":"video","content_id":"1043309521","content_offset_seconds":1484,"commenter":{"display_name":"loumoens","_id":"631617218","name":"loumoens","bio":null,"created_at":"2021-01-05T19:41:48.570158Z","updated_at":"2022-05-12T17:59:16.274538Z","logo":"https://static-cdn.jtvnw.net/user-default-pictures-uv/ebb84563-db81-4b9c-8940-64ed33ccfc7b-profile_image-300x300.png"},"message":{"body":"scope","bits_spent":0,"fragments":[{"text":"scope","emoticon":null}],"user_badges":[{"_id":"subscriber","version":"0"}],"user_color":null,"emoticons":[]}},{"_id":"kamAFSDChBby8w","created_at":"2021-06-02T12:00:08.0936814Z","channel_id":"66133267","content_type":"video","content_id":"1043309521","content_offset_seconds":1495,"commenter":{"display_name":"iamaprincess2","_id":"543182709","name":"iamaprincess2","bio":null,"created_at":"2020-06-13T15:54:25.41111Z","updated_at":"2024-03-26T19:14:45.909137Z","logo":"https://static-cdn.jtvnw.net/user-default-pictures-uv/41780b5a-def8-11e9-94d9-784f43822e80-profile_image-300x300.png"},"message":{"body":"@siemenswek ik ben een vrouw da is er gebeurd","bits_spent":0,"fragments":[{"text":"@siemenswek","emoticon":null},{"text":" ik ben een vrouw da is er gebeurd","emoticon":null}],"user_badges":[{"_id":"moderator","version":"1"},{"_id":"subscriber","version":"3"}],"user_color":"#FF69B4","emoticons":[]}},{"_id":"iLOAFSDChBYWWQ","created_at":"2021-06-02T12:00:08.166011Z","channel_id":"66133267","content_type":"video","content_id":"1043309521","content_offset_seconds":1496,"commenter":{"display_name":"siemenswek","_id":"74532248","name":"siemenswek","bio":"DAG, Ik ben Siemen, 23, software tester en fervent gamer. ik ben weliswaar dogwater in elke game die ik speel maar ben de beste entertainer ter wereld (van mijn huis)","created_at":"2014-11-05T14:25:08.031979Z","updated_at":"2024-04-01T11:44:06.480947Z","logo":"https://static-cdn.jtvnw.net/jtv_user_pictures/759a58ab-1907-4387-b7b0-65b026646281-profile_image-300x300.jpeg"},"message":{"body":"@rocca017 mini reflex vind hij beter idk","bits_spent":0,"fragments":[{"text":"@rocca017","emoticon":null},{"text":" mini reflex vind hij beter idk","emoticon":null}],"user_badges":[{"_id":"moderator","version":"1"}],"user_color":"#FF69B4","emoticons":[]}},{"_id":"sL2AFSDChBYefA","created_at":"2021-06-02T12:00:08.235157Z","channel_id":"66133267","content_type":"video","content_id":"1043309521","content_offset_seconds":1503,"commenter":{"display_name":"Nightbot","_id":"19264788","name":"nightbot","bio":"A chat moderation bot on Twitch. Visit nightbot.com to add Nightbot to your stream.","created_at":"2011-01-05T00:34:05.973707Z","updated_at":"2023-09-19T19:22:52.563766Z","logo":"https://static-cdn.jtvnw.net/jtv_user_pictures/nightbot-profile_image-2345338c09b4d468-300x300.png"},"message":{"body":"Join my Discord, Let's build a community!! https://discord.gg/7rWUsv6ZKz","bits_spent":0,"fragments":[{"text":"Join my Discord, Let's build a community!! ","emoticon":null},{"text":"https://discord.gg/7rWUsv6ZKz","emoticon":null}],"user_badges":[{"_id":"moderator","version":"1"},{"_id":"subscriber","version":"2"},{"_id":"partner","version":"1"}],"user_color":"#7C7CE1","emoticons":[]}},{"_id":"2seAFSDChBbO_Q","created_at":"2021-06-02T12:00:08.2848114Z","channel_id":"66133267","content_type":"video","content_id":"1043309521","content_offset_seconds":1525,"commenter":{"display_name":"bryan18k","_id":"123888265","name":"bryan18k","bio":"Welkom iedereen Op Mijn Twitch kanaal Ben Bryan, Ik ben 25 jaar oud   ik woon in Belgié Oost-Vlaanderen ik wil altijd het beste voor mijn stream & community  als ik niet Live ben Volg me even & dan kunt gy me altijd Checken Alvast Bedankt Voor het volgen van mijn kanaal","created_at":"2016-05-09T19:54:44.457564Z","updated_at":"2024-03-06T15:11:36.209426Z","logo":"https://static-cdn.jtvnw.net/jtv_user_pictures/1b997e3a-7f5f-42f3-aa40-2e255e757610-profile_image-300x300.png"},"message":{"body":"Wrm enkel Engelse laaste dagen maatje","bits_spent":0,"fragments":[{"text":"Wrm enkel Engelse laaste dagen maatje","emoticon":null}],"user_badges":[],"user_color":"#0000FF","emoticons":[]}},{"_id":"Q9KAFSDChBYU1g","created_at":"2021-06-02T12:00:08.3275637Z","channel_id":"66133267","content_type":"video","content_id":"1043309521","content_offset_seconds":1527,"commenter":{"display_name":"siemenswek","_id":"74532248","name":"siemenswek","bio":"DAG, Ik ben Siemen, 23, software tester en fervent gamer. ik ben weliswaar dogwater in elke game die ik speel maar ben de beste entertainer ter wereld (van mijn huis)","created_at":"2014-11-05T14:25:08.031979Z","updated_at":"2024-04-01T11:44:06.480947Z","logo":"https://static-cdn.jtvnw.net/jtv_user_pictures/759a58ab-1907-4387-b7b0-65b026646281-profile_image-300x300.jpeg"},"message":{"body":"@iamaprincess2 ah zo ne dag","bits_spent":0,"fragments":[{"text":"@iamaprincess2","emoticon":null},{"text":" ah zo ne dag","emoticon":null}],"user_badges":[{"_id":"moderator","version":"1"}],"user_color":"#FF69B4","emoticons":[]}},{"_id":"Z9yAFSDChBZA8g","created_at":"2021-06-02T12:00:08.5062948Z","channel_id":"66133267","content_type":"video","content_id":"1043309521","content_offset_seconds":1558,"commenter":{"display_name":"シシシシシシシシシシシ","_id":"15439691","name":"fatstarl0rd","bio":"","created_at":"2010-09-10T22:17:59.278724Z","updated_at":"2024-04-01T21:40:29.763228Z","logo":"https://static-cdn.jtvnw.net/jtv_user_pictures/73482d9c-b2d2-49d6-a7fa-dde1abdca150-profile_image-300x300.png"},"message":{"body":"@siemenswek week* LUL","bits_spent":0,"fragments":[{"text":"@siemenswek","emoticon":null},{"text":" week* ","emoticon":null},{"text":"LUL","emoticon":{"emoticon_id":"425618"}}],"user_badges":[{"_id":"moderator","version":"1"},{"_id":"subscriber","version":"3"},{"_id":"premium","version":"1"}],"user_color":"#FF69B4","emoticons":[{"_id":"425618","begin":18,"end":22}]}},{"_id":"5VGBFSDChBaetg","created_at":"2021-06-02T12:00:08.5629682Z","channel_id":"66133267","content_type":"video","content_id":"1043309521","content_offset_seconds":1572,"commenter":{"display_name":"Rocca017","_id":"195145656","name":"rocca017","bio":null,"created_at":"2018-02-07T01:14:37.608043Z","updated_at":"2024-03-12T16:30:24.177501Z","logo":"https://static-cdn.jtvnw.net/jtv_user_pictures/3ce9832e-9c4f-4c43-9853-f68f7787fcc9-profile_image-300x300.png"},"message":{"body":"@vlemety nope","bits_spent":0,"fragments":[{"text":"@vlemety","emoticon":null},{"text":" nope","emoticon":null}],"user_badges":[{"_id":"moderator","version":"1"},{"_id":"subscriber","version":"6"},{"_id":"premium","version":"1"}],"user_color":"#693273","emoticons":[]}},{"_id":"jGWBFSDChBbE9g","created_at":"2021-06-02T12:00:08.609196Z","channel_id":"66133267","content_type":"video","content_id":"1043309521","content_offset_seconds":1574,"commenter":{"display_name":"Rocca017","_id":"195145656","name":"rocca017","bio":null,"created_at":"2018-02-07T01:14:37.608043Z","updated_at":"2024-03-12T16:30:24.177501Z","logo":"https://static-cdn.jtvnw.net/jtv_user_pictures/3ce9832e-9c4f-4c43-9853-f68f7787fcc9-profile_image-300x300.png"},"message":{"body":"!vrienden","bits_spent":0,"fragments":[{"text":"!vrienden","emoticon":null}],"user_badges":[{"_id":"moderator","version":"1"},{"_id":"subscriber","version":"6"},{"_id":"premium","version":"1"}],"user_color":"#693273","emoticons":[]}},{"_id":"VnCBFSDChBZ51Q","created_at":"2021-06-02T12:00:08.6513865Z","channel_id":"66133267","content_type":"video","content_id":"1043309521","content_offset_seconds":1574,"commenter":{"display_name":"Nightbot","_id":"19264788","name":"nightbot","bio":"A chat moderation bot on Twitch. Visit nightbot.com to add Nightbot to your stream.","created_at":"2011-01-05T00:34:05.973707Z","updated_at":"2023-09-19T19:22:52.563766Z","logo":"https://static-cdn.jtvnw.net/jtv_user_pictures/nightbot-profile_image-2345338c09b4d468-300x300.png"},"message":{"body":"Als ik met mijn IRL vrienden speel kan ik niet met kijkers spelen, ik speel zeker en vast ook met kijkers maar niet op dit moment!!","bits_spent":0,"fragments":[{"text":"Als ik met mijn IRL vrienden speel kan ik niet met kijkers spelen, ik speel zeker en vast ook met kijkers maar niet op dit moment!!","emoticon":null}],"user_badges":[{"_id":"moderator","version":"1"},{"_id":"subscriber","version":"2"},{"_id":"partner","version":"1"}],"user_color":"#7C7CE1","emoticons":[]}},{"_id":"nHuBFSDChBapMg","created_at":"2021-06-02T12:00:08.7052724Z","channel_id":"66133267","content_type":"video","content_id":"1043309521","content_offset_seconds":1575,"commenter":{"display_name":"iamaprincess2","_id":"543182709","name":"iamaprincess2","bio":null,"created_at":"2020-06-13T15:54:25.41111Z","updated_at":"2024-03-26T19:14:45.909137Z","logo":"https://static-cdn.jtvnw.net/user-default-pictures-uv/41780b5a-def8-11e9-94d9-784f43822e80-profile_image-300x300.png"},"message":{"body":"@siemenswek dagen tis ne 5 daagse lol","bits_spent":0,"fragments":[{"text":"@siemenswek","emoticon":null},{"text":" dagen tis ne 5 daagse lol","emoticon":null}],"user_badges":[{"_id":"moderator","version":"1"},{"_id":"subscriber","version":"3"}],"user_color":"#FF69B4","emoticons":[]}},{"_id":"7oWBFSDChBaxfw","created_at":"2021-06-02T12:00:08.7582729Z","channel_id":"66133267","content_type":"video","content_id":"1043309521","content_offset_seconds":1603,"commenter":{"display_name":"siemenswek","_id":"74532248","name":"siemenswek","bio":"DAG, Ik ben Siemen, 23, software tester en fervent gamer. ik ben weliswaar dogwater in elke game die ik speel maar ben de beste entertainer ter wereld (van mijn huis)","created_at":"2014-11-05T14:25:08.031979Z","updated_at":"2024-04-01T11:44:06.480947Z","logo":"https://static-cdn.jtvnw.net/jtv_user_pictures/759a58ab-1907-4387-b7b0-65b026646281-profile_image-300x300.jpeg"},"message":{"body":"@iamaprincess2 huh","bits_spent":0,"fragments":[{"text":"@iamaprincess2","emoticon":null},{"text":" huh","emoticon":null}],"user_badges":[{"_id":"moderator","version":"1"}],"user_color":"#FF69B4","emoticons":[]}}],"embeddedData":null}