{"FileInfo":{"Version":{"Major":1,"Minor":3,"Patch":1},"CreatedAt":"2024-04-01T23:55:35.5998607+02:00","UpdatedAt":"0001-01-01T00:00:00"},"streamer":{"name":"MichielVandeweert","id":66133267},"video":{"title":"rebirth win","description":null,"id":"1071232784","created_at":"2021-06-29T13:23:54Z","start":0,"end":805,"length":805,"viewCount":1,"game":"Call of Duty: Warzone","chapters":[{"id":"","startMilliseconds":0,"lengthMilliseconds":805000,"type":"GAME_CHANGE","description":"Call of Duty: Warzone","subDescription":"","thumbnailUrl":null,"gameId":"512710","gameDisplayName":"Call of Duty: Warzone","gameBoxArtUrl":"https://static-cdn.jtvnw.net/ttv-boxart/512710-40x53.jpg"}]},"comments":[{"_id":"RmdCkXkQjRafEg","created_at":"2021-06-29T13:25:54.8644276Z","channel_id":"66133267","content_type":"video","content_id":"1071232784","content_offset_seconds":64,"commenter":{"display_name":"iRxwzy","_id":"163326980","name":"irxwzy","bio":"hi, I play a tons of games  I am 23  y/O birthday 18/05 also a party animal ","created_at":"2017-07-07T18:50:24.796289Z","updated_at":"2024-02-05T16:49:44.249725Z","logo":"https://static-cdn.jtvnw.net/jtv_user_pictures/231a8fed-71ed-4db6-afb4-2773d9287abd-profile_image-300x300.png"},"message":{"body":"ben aan het kijken voor de scar denk word wel nieuwe meta","bits_spent":0,"fragments":[{"text":"ben aan het kijken voor de scar denk word wel nieuwe meta","emoticon":null}],"user_badges":[{"_id":"premium","version":"1"}],"user_color":"#FF0000","emoticons":[]}},{"_id":"vYJCkXkQjRYtpg","created_at":"2021-06-29T13:25:54.8644324Z","channel_id":"66133267","content_type":"video","content_id":"1071232784","content_offset_seconds":69,"commenter":{"display_name":"wil_de_pijperrr","_id":"260566345","name":"wil_de_pijperrr","bio":"why are you looking here dude go back","created_at":"2018-09-19T14:13:02.911463Z","updated_at":"2024-04-01T17:38:27.742771Z","logo":"https://static-cdn.jtvnw.net/jtv_user_pictures/6aeb55b3-21d8-4520-b3c5-608315861e73-profile_image-300x300.png"},"message":{"body":"<3","bits_spent":0,"fragments":[{"text":"<3","emoticon":{"emoticon_id":"445"}}],"user_badges":[{"_id":"premium","version":"1"}],"user_color":null,"emoticons":[{"_id":"445","begin":0,"end":3}]}},{"_id":"-YxCkXkQjRYYUg","created_at":"2021-06-29T13:25:54.8644363Z","channel_id":"66133267","content_type":"video","content_id":"1071232784","content_offset_seconds":73,"commenter":{"display_name":"Rocca017","_id":"195145656","name":"rocca017","bio":null,"created_at":"2018-02-07T01:14:37.608043Z","updated_at":"2024-03-12T16:30:24.177501Z","logo":"https://static-cdn.jtvnw.net/jtv_user_pictures/3ce9832e-9c4f-4c43-9853-f68f7787fcc9-profile_image-300x300.png"},"message":{"body":"ik ben gewoon voorstander van de gewone suppressor voor de ads speed die beter is :)","bits_spent":0,"fragments":[{"text":"ik ben gewoon voorstander van de gewone suppressor voor de ads speed die beter is ","emoticon":null},{"text":":)","emoticon":{"emoticon_id":"1"}}],"user_badges":[{"_id":"moderator","version":"1"},{"_id":"subscriber","version":"6"},{"_id":"premium","version":"1"}],"user_color":"#693273","emoticons":[{"_id":"1","begin":82,"end":85}]}},{"_id":"xZdCkXkQjRZo3w","created_at":"2021-06-29T13:25:54.8644398Z","channel_id":"66133267","content_type":"video","content_id":"1071232784","content_offset_seconds":83,"commenter":{"display_name":"Rocca017","_id":"195145656","name":"rocca017","bio":null,"created_at":"2018-02-07T01:14:37.608043Z","updated_at":"2024-03-12T16:30:24.177501Z","logo":"https://static-cdn.jtvnw.net/jtv_user_pictures/3ce9832e-9c4f-4c43-9853-f68f7787fcc9-profile_image-300x300.png"},"message":{"body":"@iRxwzy nieuwe meta is er al :)","bits_spent":0,"fragments":[{"text":"@iRxwzy nieuwe meta is er al ","emoticon":null},{"text":":)","emoticon":{"emoticon_id":"1"}}],"user_badges":[{"_id":"moderator","version":"1"},{"_id":"subscriber","version":"6"},{"_id":"premium","version":"1"}],"user_color":"#693273","emoticons":[{"_id":"1","begin":29,"end":32}]}},{"_id":"p6FCkXkQjRYufw","created_at":"2021-06-29T13:25:54.8644426Z","channel_id":"66133267","content_type":"video","content_id":"1071232784","content_offset_seconds":101,"commenter":{"display_name":"iRxwzy","_id":"163326980","name":"irxwzy","bio":"hi, I play a tons of games  I am 23  y/O birthday 18/05 also a party animal ","created_at":"2017-07-07T18:50:24.796289Z","updated_at":"2024-02-05T16:49:44.249725Z","logo":"https://static-cdn.jtvnw.net/jtv_user_pictures/231a8fed-71ed-4db6-afb4-2773d9287abd-profile_image-300x300.png"},"message":{"body":"@Rocca017 welke dan","bits_spent":0,"fragments":[{"text":"@Rocca017 welke dan","emoticon":null}],"user_badges":[{"_id":"premium","version":"1"}],"user_color":"#FF0000","emoticons":[]}},{"_id":"zatCkXkQjRbdEQ","created_at":"2021-06-29T13:25:54.8644475Z","channel_id":"66133267","content_type":"video","content_id":"1071232784","content_offset_seconds":104,"commenter":{"display_name":"Rocca017","_id":"195145656","name":"rocca017","bio":null,"created_at":"2018-02-07T01:14:37.608043Z","updated_at":"2024-03-12T16:30:24.177501Z","logo":"https://static-cdn.jtvnw.net/jtv_user_pictures/3ce9832e-9c4f-4c43-9853-f68f7787fcc9-profile_image-300x300.png"},"message":{"body":"@iRxwzy MG82","bits_spent":0,"fragments":[{"text":"@iRxwzy MG82","emoticon":null}],"user_badges":[{"_id":"moderator","version":"1"},{"_id":"subscriber","version":"6"},{"_id":"premium","version":"1"}],"user_color":"#693273","emoticons":[]}},{"_id":"qLVCkXkQjRaYvQ","created_at":"2021-06-29T13:25:54.8644504Z","channel_id":"66133267","content_type":"video","content_id":"1071232784","content_offset_seconds":114,"commenter":{"display_name":"iRxwzy","_id":"163326980","name":"irxwzy","bio":"hi, I play a tons of games  I am 23  y/O birthday 18/05 also a party animal ","created_at":"2017-07-07T18:50:24.796289Z","updated_at":"2024-02-05T16:49:44.249725Z","logo":"https://static-cdn.jtvnw.net/jtv_user_pictures/231a8fed-71ed-4db6-afb4-2773d9287abd-profile_image-300x300.png"},"message":{"body":"ugh haat dat ding zo hard","bits_spent":0,"fragments":[{"text":"ugh haat dat ding zo hard","emoticon":null}],"user_badges":[{"_id":"premium","version":"1"}],"user_color":"#FF0000","emoticons":[]}},{"_id":"V8lCkXkQjRZXoA","created_at":"2021-06-29T13:25:54.8644568Z","channel_id":"66133267","content_type":"video","content_id":"1071232784","content_offset_seconds":122,"commenter":{"display_name":"iRxwzy","_id":"163326980","name":"irxwzy","bio":"hi, I play a tons of games  I am 23  y/O birthday 18/05 also a party animal ","created_at":"2017-07-07T18:50:24.796289Z","updated_at":"2024-02-05T16:49:44.249725Z","logo":"https://static-cdn.jtvnw.net/jtv_user_pictures/231a8fed-71ed-4db6-afb4-2773d9287abd-profile_image-300x300.png"},"message":{"body":"da ding moge ze oprecht nerfen","bits_spent":0,"fragments":[{"text":"da ding moge ze oprecht nerfen","emoticon":null}],"user_badges":[{"_id":"premium","version":"1"}],"user_color":"#FF0000","emoticons":[]}},{"_id":"ONNCkXkQjRZ08Q","created_at":"2021-06-29T13:25:54.864461Z","channel_id":"66133267","content_type":"video","content_id":"1071232784","content_offset_seconds":142,"commenter":{"display_name":"Rocca017","_id":"195145656","name":"rocca017","bio":null,"created_at":"2018-02-07T01:14:37.608043Z","updated_at":"2024-03-12T16:30:24.177501Z","logo":"https://static-cdn.jtvnw.net/jtv_user_pictures/3ce9832e-9c4f-4c43-9853-f68f7787fcc9-profile_image-300x300.png"},"message":{"body":"moeten ze gewoon doen :)","bits_spent":0,"fragments":[{"text":"moeten ze gewoon doen ","emoticon":null},{"text":":)","emoticon":{"emoticon_id":"1"}}],"user_badges":[{"_id":"moderator","version":"1"},{"_id":"subscriber","version":"6"},{"_id":"premium","version":"1"}],"user_color":"#693273","emoticons":[{"_id":"1","begin":22,"end":25}]}},{"_id":"V91CkXkQjRYkYA","created_at":"2021-06-29T13:25:54.8644669Z","channel_id":"66133267","content_type":"video","content_id":"1071232784","content_offset_seconds":195,"commenter":{"display_name":"Rocca017","_id":"195145656","name":"rocca017","bio":null,"created_at":"2018-02-07T01:14:37.608043Z","updated_at":"2024-03-12T16:30:24.177501Z","logo":"https://static-cdn.jtvnw.net/jtv_user_pictures/3ce9832e-9c4f-4c43-9853-f68f7787fcc9-profile_image-300x300.png"},"message":{"body":"kijk ik praat over cold war ... gewone suppressor = sound suppressor voor mij :)","bits_spent":0,"fragments":[{"text":"kijk ik praat over cold war ... gewone suppressor = sound suppressor voor mij ","emoticon":null},{"text":":)","emoticon":{"emoticon_id":"1"}}],"user_badges":[{"_id":"moderator","version":"1"},{"_id":"subscriber","version":"6"},{"_id":"premium","version":"1"}],"user_color":"#693273","emoticons":[{"_id":"1","begin":78,"end":81}]}},{"_id":"eedCkXkQjRYuXw","created_at":"2021-06-29T13:25:54.8644697Z","channel_id":"66133267","content_type":"video","content_id":"1071232784","content_offset_seconds":229,"commenter":{"display_name":"Rocca017","_id":"195145656","name":"rocca017","bio":null,"created_at":"2018-02-07T01:14:37.608043Z","updated_at":"2024-03-12T16:30:24.177501Z","logo":"https://static-cdn.jtvnw.net/jtv_user_pictures/3ce9832e-9c4f-4c43-9853-f68f7787fcc9-profile_image-300x300.png"},"message":{"body":"die moto is ALI :D geef toe doet u toch aan haar denken :D","bits_spent":0,"fragments":[{"text":"die moto is ALI ","emoticon":null},{"text":":D","emoticon":{"emoticon_id":"555555560"}},{"text":" geef toe doet u toch aan haar denken ","emoticon":null},{"text":":D","emoticon":{"emoticon_id":"555555560"}}],"user_badges":[{"_id":"moderator","version":"1"},{"_id":"subscriber","version":"6"},{"_id":"premium","version":"1"}],"user_color":"#693273","emoticons":[{"_id":"555555560","begin":16,"end":19},{"_id":"555555560","begin":56,"end":59}]}},{"_id":"j_FCkXkQjRaKUg","created_at":"2021-06-29T13:25:54.8644728Z","channel_id":"66133267","content_type":"video","content_id":"1071232784","content_offset_seconds":238,"commenter":{"display_name":"Rocca017","_id":"195145656","name":"rocca017","bio":null,"created_at":"2018-02-07T01:14:37.608043Z","updated_at":"2024-03-12T16:30:24.177501Z","logo":"https://static-cdn.jtvnw.net/jtv_user_pictures/3ce9832e-9c4f-4c43-9853-f68f7787fcc9-profile_image-300x300.png"},"message":{"body":"klinkt als een K3 liedje wat ze aan het zingen is :D","bits_spent":0,"fragments":[{"text":"klinkt als een K3 liedje wat ze aan het zingen is ","emoticon":null},{"text":":D","emoticon":{"emoticon_id":"555555560"}}],"user_badges":[{"_id":"moderator","version":"1"},{"_id":"subscriber","version":"6"},{"_id":"premium","version":"1"}],"user_color":"#693273","emoticons":[{"_id":"555555560","begin":50,"end":53}]}},{"_id":"fQVDkXkQjRY-Zw","created_at":"2021-06-29T13:25:54.8644788Z","channel_id":"66133267","content_type":"video","content_id":"1071232784","content_offset_seconds":316,"commenter":{"display_name":"Nightbot","_id":"19264788","name":"nightbot","bio":"A chat moderation bot on Twitch. Visit nightbot.com to add Nightbot to your stream.","created_at":"2011-01-05T00:34:05.973707Z","updated_at":"2023-09-19T19:22:52.563766Z","logo":"https://static-cdn.jtvnw.net/jtv_user_pictures/nightbot-profile_image-2345338c09b4d468-300x300.png"},"message":{"body":"I drink Guice Energy during my streams! I'm always feeling tired, but Guice gives me that energy to stream everyday, it's honestly an amazing product! Use my code: Michiel for 15% off https://guiceenergy.eu/","bits_spent":0,"fragments":[{"text":"I drink Guice Energy during my streams! I'm always feeling tired, but Guice gives me that energy to stream everyday, it's honestly an amazing product! Use my code: Michiel for 15% off https://guiceenergy.eu/","emoticon":null}],"user_badges":[{"_id":"moderator","version":"1"},{"_id":"subscriber","version":"3"},{"_id":"partner","version":"1"}],"user_color":"#7C7CE1","emoticons":[]}},{"_id":"Zg9DkXkQjRZqfg","created_at":"2021-06-29T13:25:54.864482Z","channel_id":"66133267","content_type":"video","content_id":"1071232784","content_offset_seconds":393,"commenter":{"display_name":"dangilos_nmgn","_id":"616043269","name":"dangilos_nmgn","bio":"hello guys I'm Dangilos_nmgn i weekly stream Valorant, Fortnite, Grand theft auto and/or Minecraft, u can follow me if you want its for free.","created_at":"2020-12-03T13:58:04.903979Z","updated_at":"2023-12-20T18:58:04.996775Z","logo":"https://static-cdn.jtvnw.net/jtv_user_pictures/0daf46c7-2637-4692-9956-c1df07d0cce8-profile_image-300x300.png"},"message":{"body":"eeey mie ik ga niet meer zo vaak noline zijn meer. het gaat niet zo heel goed met mijn familie door corona enz. ik blijf nog wel bij de stream vandaag maar volgende week weet ik niet meer man","bits_spent":0,"fragments":[{"text":"eeey mie ik ga niet meer zo vaak noline zijn meer. het gaat niet zo heel goed met mijn familie door corona enz. ik blijf nog wel bij de stream vandaag maar volgende week weet ik niet meer man","emoticon":null}],"user_badges":[],"user_color":"#FF0000","emoticons":[]}},{"_id":"GhtDkXkQjRbDuA","created_at":"2021-06-29T13:25:54.8644849Z","channel_id":"66133267","content_type":"video","content_id":"1071232784","content_offset_seconds":420,"commenter":{"display_name":"Nightbot","_id":"19264788","name":"nightbot","bio":"A chat moderation bot on Twitch. Visit nightbot.com to add Nightbot to your stream.","created_at":"2011-01-05T00:34:05.973707Z","updated_at":"2023-09-19T19:22:52.563766Z","logo":"https://static-cdn.jtvnw.net/jtv_user_pictures/nightbot-profile_image-2345338c09b4d468-300x300.png"},"message":{"body":"@ampultiesss -> My name is Michiel just call me that :) [warning]","bits_spent":0,"fragments":[{"text":"@ampultiesss -> My name is Michiel just call me that ","emoticon":null},{"text":":)","emoticon":{"emoticon_id":"499"}},{"text":" [warning]","emoticon":null}],"user_badges":[{"_id":"moderator","version":"1"},{"_id":"subscriber","version":"3"},{"_id":"partner","version":"1"}],"user_color":"#7C7CE1","emoticons":[{"_id":"499","begin":53,"end":56}]}},{"_id":"KiRDkXkQjRZGxA","created_at":"2021-06-29T13:25:54.8644907Z","channel_id":"66133267","content_type":"video","content_id":"1071232784","content_offset_seconds":550,"commenter":{"display_name":"witse10max","_id":"505561316","name":"witse10max","bio":null,"created_at":"2020-03-29T14:49:20.272615Z","updated_at":"2023-12-02T18:55:19.564433Z","logo":"https://static-cdn.jtvnw.net/jtv_user_pictures/41477958-244f-410c-a592-208afe0f9810-profile_image-300x300.png"},"message":{"body":"jow man ik hoop dat het goed gaat met jou","bits_spent":0,"fragments":[{"text":"jow man ik hoop dat het goed gaat met jou","emoticon":null}],"user_badges":[],"user_color":null,"emoticons":[]}},{"_id":"VC5DkXkQjRYggQ","created_at":"2021-06-29T13:25:54.8644944Z","channel_id":"66133267","content_type":"video","content_id":"1071232784","content_offset_seconds":554,"commenter":{"display_name":"Nightbot","_id":"19264788","name":"nightbot","bio":"A chat moderation bot on Twitch. Visit nightbot.com to add Nightbot to your stream.","created_at":"2011-01-05T00:34:05.973707Z","updated_at":"2023-09-19T19:22:52.563766Z","logo":"https://static-cdn.jtvnw.net/jtv_user_pictures/nightbot-profile_image-2345338c09b4d468-300x300.png"},"message":{"body":"@ampultiesss -> My name is Michiel just call me that :)","bits_spent":0,"fragments":[{"text":"@ampultiesss -> My name is Michiel just call me that ","emoticon":null},{"text":":)","emoticon":{"emoticon_id":"499"}}],"user_badges":[{"_id":"moderator","version":"1"},{"_id":"subscriber","version":"3"},{"_id":"partner","version":"1"}],"user_color":"#7C7CE1","emoticons":[{"_id":"499","begin":53,"end":56}]}},{"_id":"VDhDkXkQjRbYNA","created_at":"2021-06-29T13:25:54.8644972Z","channel_id":"66133267","content_type":"video","content_id":"1071232784","content_offset_seconds":589,"commenter":{"display_name":"witse10max","_id":"505561316","name":"witse10max","bio":null,"created_at":"2020-03-29T14:49:20.272615Z","updated_at":"2023-12-02T18:55:19.564433Z","logo":"https://static-cdn.jtvnw.net/jtv_user_pictures/41477958-244f-410c-a592-208afe0f9810-profile_image-300x300.png"},"message":{"body":"ehm lekker","bits_spent":0,"fragments":[{"text":"ehm lekker","emoticon":null}],"user_badges":[],"user_color":null,"emoticons":[]}},{"_id":"GEJDkXkQjRaqiQ","created_at":"2021-06-29T13:25:54.8645005Z","channel_id":"66133267","content_type":"video","content_id":"1071232784","content_offset_seconds":592,"commenter":{"display_name":"dangilos_nmgn","_id":"616043269","name":"dangilos_nmgn","bio":"hello guys I'm Dangilos_nmgn i weekly stream Valorant, Fortnite, Grand theft auto and/or Minecraft, u can follow me if you want its for free.","created_at":"2020-12-03T13:58:04.903979Z","updated_at":"2023-12-20T18:58:04.996775Z","logo":"https://static-cdn.jtvnw.net/jtv_user_pictures/0daf46c7-2637-4692-9956-c1df07d0cce8-profile_image-300x300.png"},"message":{"body":"@witse10max met mij wel hoor maar met andere niet zo goed in mn familie bijv mn oma. ik wil liever hier niet meer over praten man","bits_spent":0,"fragments":[{"text":"@witse10max met mij wel hoor maar met andere niet zo goed in mn familie bijv mn oma. ik wil liever hier niet meer over praten man","emoticon":null}],"user_badges":[],"user_color":"#FF0000","emoticons":[]}},{"_id":"8EtDkXkQjRZJbg","created_at":"2021-06-29T13:25:54.8645042Z","channel_id":"66133267","content_type":"video","content_id":"1071232784","content_offset_seconds":594,"commenter":{"display_name":"witse10max","_id":"505561316","name":"witse10max","bio":null,"created_at":"2020-03-29T14:49:20.272615Z","updated_at":"2023-12-02T18:55:19.564433Z","logo":"https://static-cdn.jtvnw.net/jtv_user_pictures/41477958-244f-410c-a592-208afe0f9810-profile_image-300x300.png"},"message":{"body":"komaan je hebt dit","bits_spent":0,"fragments":[{"text":"komaan je hebt dit","emoticon":null}],"user_badges":[],"user_color":null,"emoticons":[]}},{"_id":"fVVDkXkQjRZIBQ","created_at":"2021-06-29T13:25:54.8647221Z","channel_id":"66133267","content_type":"video","content_id":"1071232784","content_offset_seconds":624,"commenter":{"display_name":"witse10max","_id":"505561316","name":"witse10max","bio":null,"created_at":"2020-03-29T14:49:20.272615Z","updated_at":"2023-12-02T18:55:19.564433Z","logo":"https://static-cdn.jtvnw.net/jtv_user_pictures/41477958-244f-410c-a592-208afe0f9810-profile_image-300x300.png"},"message":{"body":"@dangilos_nmgn sorry voor dat te horen man sterkte","bits_spent":0,"fragments":[{"text":"@dangilos_nmgn sorry voor dat te horen man sterkte","emoticon":null}],"user_badges":[],"user_color":null,"emoticons":[]}},{"_id":"LV9DkXkQjRaS2w","created_at":"2021-06-29T13:25:54.8647248Z","channel_id":"66133267","content_type":"video","content_id":"1071232784","content_offset_seconds":730,"commenter":{"display_name":"witse10max","_id":"505561316","name":"witse10max","bio":null,"created_at":"2020-03-29T14:49:20.272615Z","updated_at":"2023-12-02T18:55:19.564433Z","logo":"https://static-cdn.jtvnw.net/jtv_user_pictures/41477958-244f-410c-a592-208afe0f9810-profile_image-300x300.png"},"message":{"body":"ggggggg","bits_spent":0,"fragments":[{"text":"ggggggg","emoticon":null}],"user_badges":[],"user_color":null,"emoticons":[]}},{"_id":"nm1DkXkQjRakKg","created_at":"2021-06-29T13:25:54.8647269Z","channel_id":"66133267","content_type":"video","content_id":"1071232784","content_offset_seconds":735,"commenter":{"display_name":"dangilos_nmgn","_id":"616043269","name":"dangilos_nmgn","bio":"hello guys I'm Dangilos_nmgn i weekly stream Valorant, Fortnite, Grand theft auto and/or Minecraft, u can follow me if you want its for free.","created_at":"2020-12-03T13:58:04.903979Z","updated_at":"2023-12-20T18:58:04.996775Z","logo":"https://static-cdn.jtvnw.net/jtv_user_pictures/0daf46c7-2637-4692-9956-c1df07d0cce8-profile_image-300x300.png"},"message":{"body":"99","bits_spent":0,"fragments":[{"text":"99","emoticon":null}],"user_badges":[],"user_color":"#FF0000","emoticons":[]}},{"_id":"X3dDkXkQjRZHIw","created_at":"2021-06-29T13:25:54.8647289Z","channel_id":"66133267","content_type":"video","content_id":"1071232784","content_offset_seconds":735,"commenter":{"display_name":"Nightbot","_id":"19264788","name":"nightbot","bio":"A chat moderation bot on Twitch. Visit nightbot.com to add Nightbot to your stream.","created_at":"2011-01-05T00:34:05.973707Z","updated_at":"2023-09-19T19:22:52.563766Z","logo":"https://static-cdn.jtvnw.net/jtv_user_pictures/nightbot-profile_image-2345338c09b4d468-300x300.png"},"message":{"body":"michie299","bits_spent":0,"fragments":[{"text":"michie299","emoticon":{"emoticon_id":"307025572"}}],"user_badges":[{"_id":"moderator","version":"1"},{"_id":"subscriber","version":"3"},{"_id":"partner","version":"1"}],"user_color":"#7C7CE1","emoticons":[{"_id":"307025572","begin":0,"end":10}]}},{"_id":"7oBDkXkQjRanbA","created_at":"2021-06-29T13:25:54.8647309Z","channel_id":"66133267","content_type":"video","content_id":"1071232784","content_offset_seconds":738,"commenter":{"display_name":"MichielVandeweert","_id":"66133267","name":"michielvandeweert","bio":"Belgian #1 PROgeria gamer // Best gaming content 2023 Jamie award winner // Collaboration: management@mastr.be\t","created_at":"2014-07-11T23:03:09.081516Z","updated_at":"2024-03-28T17:04:39.830748Z","logo":"https://static-cdn.jtvnw.net/jtv_user_pictures/55be6eff-5053-4d65-8625-ced2c075f0fb-profile_image-300x300.png"},"message":{"body":"michie299 michie299","bits_spent":0,"fragments":[{"text":"michie299","emoticon":{"emoticon_id":"307025572"}},{"text":" ","emoticon":null},{"text":"michie299","emoticon":{"emoticon_id":"307025572"}}],"user_badges":[{"_id":"broadcaster","version":"1"}],"user_color":"#00FF7F","emoticons":[{"_id":"307025572","begin":0,"end":10},{"_id":"307025572","begin":10,"end":20}]}},{"_id":"hYpDkXkQjRbJig","created_at":"2021-06-29T13:25:54.8647328Z","channel_id":"66133267","content_type":"video","content_id":"1071232784","content_offset_seconds":738,"commenter":{"display_name":"MichielVandeweert","_id":"66133267","name":"michielvandeweert","bio":"Belgian #1 PROgeria gamer // Best gaming content 2023 Jamie award winner // Collaboration: management@mastr.be\t","created_at":"2014-07-11T23:03:09.081516Z","updated_at":"2024-03-28T17:04:39.830748Z","logo":"https://static-cdn.jtvnw.net/jtv_user_pictures/55be6eff-5053-4d65-8625-ced2c075f0fb-profile_image-300x300.png"},"message":{"body":"michie299 michie299","bits_spent":0,"fragments":[{"text":"michie299","emoticon":{"emoticon_id":"307025572"}},{"text":" ","emoticon":null},{"text":"michie299","emoticon":{"emoticon_id":"307025572"}}],"user_badges":[{"_id":"broadcaster","version":"1"}],"user_color":"#00FF7F","emoticons":[{"_id":"307025572","begin":0,"end":10},{"_id":"307025572","begin":10,"end":20}]}},{"_id":"MZRDkXkQjRZT2A","created_at":"2021-06-29T13:25:54.8647348Z","channel_id":"66133267","content_type":"video","content_id":"1071232784","content_offset_seconds":739,"commenter":{"display_name":"dangilos_nmgn","_id":"616043269","name":"dangilos_nmgn","bio":"hello guys I'm Dangilos_nmgn i weekly stream Valorant, Fortnite, Grand theft auto and/or Minecraft, u can follow me if you want its for free.","created_at":"2020-12-03T13:58:04.903979Z","updated_at":"2023-12-20T18:58:04.996775Z","logo":"https://static-cdn.jtvnw.net/jtv_user_pictures/0daf46c7-2637-4692-9956-c1df07d0cce8-profile_image-300x300.png"},"message":{"body":"9999","bits_spent":0,"fragments":[{"text":"9999","emoticon":null}],"user_badges":[],"user_color":"#FF0000","emoticons":[]}},{"_id":"5Z1DkXkQjRaFvg","created_at":"2021-06-29T13:25:54.8647366Z","channel_id":"66133267","content_type":"video","content_id":"1071232784","content_offset_seconds":743,"commenter":{"display_name":"dangilos_nmgn","_id":"616043269","name":"dangilos_nmgn","bio":"hello guys I'm Dangilos_nmgn i weekly stream Valorant, Fortnite, Grand theft auto and/or Minecraft, u can follow me if you want its for free.","created_at":"2020-12-03T13:58:04.903979Z","updated_at":"2023-12-20T18:58:04.996775Z","logo":"https://static-cdn.jtvnw.net/jtv_user_pictures/0daf46c7-2637-4692-9956-c1df07d0cce8-profile_image-300x300.png"},"message":{"body":"99","bits_spent":0,"fragments":[{"text":"99","emoticon":null}],"user_badges":[],"user_color":"#FF0000","emoticons":[]}},{"_id":"CKhDkXkQjRY32Q","created_at":"2021-06-29T13:25:54.8647384Z","channel_id":"66133267","content_type":"video","content_id":"1071232784","content_offset_seconds":743,"commenter":{"display_name":"witse10max","_id":"505561316","name":"witse10max","bio":null,"created_at":"2020-03-29T14:49:20.272615Z","updated_at":"2023-12-02T18:55:19.564433Z","logo":"https://static-cdn.jtvnw.net/jtv_user_pictures/41477958-244f-410c-a592-208afe0f9810-profile_image-300x300.png"},"message":{"body":"99 99 99 99","bits_spent":0,"fragments":[{"text":"99 99 99 99","emoticon":null}],"user_badges":[],"user_color":null,"emoticons":[]}},{"_id":"-bFDkXkQjRa0-Q","created_at":"2021-06-29T13:25:54.86474Z","channel_id":"66133267","content_type":"video","content_id":"1071232784","content_offset_seconds":754,"commenter":{"display_name":"krokodillulu","_id":"683409521","name":"krokodillulu","bio":null,"created_at":"2021-05-04T14:00:31.361957Z","updated_at":"2023-03-03T14:01:43.757539Z","logo":"https://static-cdn.jtvnw.net/user-default-pictures-uv/294c98b5-e34d-42cd-a8f0-140b72fba9b0-profile_image-300x300.png"},"message":{"body":"9️⃣9️⃣ 9️⃣9️⃣ 9️⃣9️⃣ 9️⃣9️⃣ 9️⃣9️⃣ 9️⃣9️⃣ 9️⃣9️⃣ 9️⃣9️⃣","bits_spent":0,"fragments":[{"text":"9️⃣9️⃣ 9️⃣9️⃣ 9️⃣9️⃣ 9️⃣9️⃣ 9️⃣9️⃣ 9️⃣9️⃣ 9️⃣9️⃣ 9️⃣9️⃣","emoticon":null}],"user_badges":[],"user_color":null,"emoticons":[]}},{"_id":"yrtDkXkQjRaY9A","created_at":"2021-06-29T13:25:54.8647418Z","channel_id":"66133267","content_type":"video","content_id":"1071232784","content_offset_seconds":761,"commenter":{"display_name":"TheUnprocessedFoodMan","_id":"515185178","name":"theunprocessedfoodman","bio":"Stap 1. Gym. Stap2. Onbewerkt voedsel. Graag gedaan. Gelukkig nieuw jaar alvast!","created_at":"2020-04-16T15:10:46.806773Z","updated_at":"2024-04-01T20:31:28.510702Z","logo":"https://static-cdn.jtvnw.net/jtv_user_pictures/62e9af95-a995-4ca6-8d49-24bf07c3ab70-profile_image-300x300.png"},"message":{"body":"99","bits_spent":0,"fragments":[{"text":"99","emoticon":null}],"user_badges":[],"user_color":"#FF4500","emoticons":[]}},{"_id":"hMVDkXkQjRYt2g","created_at":"2021-06-29T13:25:54.8647472Z","channel_id":"66133267","content_type":"video","content_id":"1071232784","content_offset_seconds":766,"commenter":{"display_name":"Rocca017","_id":"195145656","name":"rocca017","bio":null,"created_at":"2018-02-07T01:14:37.608043Z","updated_at":"2024-03-12T16:30:24.177501Z","logo":"https://static-cdn.jtvnw.net/jtv_user_pictures/3ce9832e-9c4f-4c43-9853-f68f7787fcc9-profile_image-300x300.png"},"message":{"body":"ik snap waarom mensen dit liever spelen & waarom er zoveel vraag naar was .... dit lijkt toch veel makkelijker dan gewone warzone ?","bits_spent":0,"fragments":[{"text":"ik snap waarom mensen dit liever spelen & waarom er zoveel vraag naar was .... dit lijkt toch veel makkelijker dan gewone warzone ?","emoticon":null}],"user_badges":[{"_id":"moderator","version":"1"},{"_id":"subscriber","version":"6"},{"_id":"premium","version":"1"}],"user_color":"#693273","emoticons":[]}},{"_id":"Y89DkXkQjRYYLA","created_at":"2021-06-29T13:25:54.8647488Z","channel_id":"66133267","content_type":"video","content_id":"1071232784","content_offset_seconds":796,"commenter":{"display_name":"Rocca017","_id":"195145656","name":"rocca017","bio":null,"created_at":"2018-02-07T01:14:37.608043Z","updated_at":"2024-03-12T16:30:24.177501Z","logo":"https://static-cdn.jtvnw.net/jtv_user_pictures/3ce9832e-9c4f-4c43-9853-f68f7787fcc9-profile_image-300x300.png"},"message":{"body":"geen SBMM :D","bits_spent":0,"fragments":[{"text":"geen SBMM ","emoticon":null},{"text":":D","emoticon":{"emoticon_id":"555555560"}}],"user_badges":[{"_id":"moderator","version":"1"},{"_id":"subscriber","version":"6"},{"_id":"premium","version":"1"}],"user_color":"#693273","emoticons":[{"_id":"555555560","begin":10,"end":13}]}},{"_id":"K9pDkXkQjRZ_Sw","created_at":"2021-06-29T13:25:54.8647506Z","channel_id":"66133267","content_type":"video","content_id":"1071232784","content_offset_seconds":796,"commenter":{"display_name":"witse10max","_id":"505561316","name":"witse10max","bio":null,"created_at":"2020-03-29T14:49:20.272615Z","updated_at":"2023-12-02T18:55:19.564433Z","logo":"https://static-cdn.jtvnw.net/jtv_user_pictures/41477958-244f-410c-a592-208afe0f9810-profile_image-300x300.png"},"message":{"body":"goed gespeeld mn","bits_spent":0,"fragments":[{"text":"goed gespeeld mn","emoticon":null}],"user_badges":[],"user_color":null,"emoticons":[]}}],"embeddedData":null}